{
    "id": "tt0364845",
    "title": "NCIS",
    "originalTitle": "NCIS: Naval Criminal Investigative Service",
    "fullTitle": "NCIS (TV Series 2003– )",
    "type": "TVSeries",
    "year": "2003",
    "image": "https://imdb-api.com/images/original/MV5BYjVlMjZhYzYtOGQxNC00OTQxLTk2NzEtMWFmMmNhODA4YjYzXkEyXkFqcGdeQXVyNjQ3MDgwNjY@._V1_Ratio0.6791_AL_.jpg",
    "releaseDate": "2003-09-23",
    "runtimeMins": "60",
    "runtimeStr": "1h 0mins",
    "plot": "Special Agent Leroy Jethro Gibbs is the leader of a team of special agents belonging to the NCIS (Naval Criminal Investigative Service) Major Case Response Team. Gibbs, a former Marine, is a tough investigator and a highly skilled interrogator who relies on his gut instinct as much as evidence. Gibbs' second in command is Senior Field Agent Tony DiNozzo, a womanizing, movie-quoting former Baltimore Homicide Detective, who despite being the class clown always gets the job done. The team also consists of probationary field agent Eleanor Bishop, a former NSA agent, as well as Junior Field Agent Timothy McGee, a computer-savvy agent often mocked by DiNozzo. Assisting them are Abby Sciuto, the energetic-but-Goth lab tech who is like a daughter to Gibbs, and Dr. Donald Mallard, nicknamed Ducky, the eccentric medical examiner full of unusual stories. This team of elite agents, based in Washington, D.C., solve criminal cases involving Marine and Navy personnel and their families, sometimes ...",
    "plotLocal": "",
    "plotLocalIsRtl": false,
    "awards": "Nominated for 3 Primetime Emmys. Another 27 wins & 37 nominations.",
    "directors": "",
    "directorList": [],
    "writers": "",
    "writerList": [],
    "stars": "Mark Harmon, David McCallum, Sean Murray, Pauley Perrette",
    "starList": [
        { "id": "nm0001319", "name": "Mark Harmon" },
        { "id": "nm0564724", "name": "David McCallum" },
        { "id": "nm0615266", "name": "Sean Murray" },
        { "id": "nm0005306", "name": "Pauley Perrette" }
    ],
    "actorList": [
        {
            "id": "nm0001319",
            "image": "https://imdb-api.com/images/original/MV5BMTU0NTU3OTU3NF5BMl5BanBnXkFtZTYwODg2NDE1._V1_Ratio0.7273_AL_.jpg",
            "name": "Mark Harmon",
            "asCharacter": "Leroy Jethro Gibbs / ... 412 episodes, 2003-2021"
        },
        {
            "id": "nm0564724",
            "image": "https://imdb-api.com/images/original/MV5BNDkzMDE5OTU0OV5BMl5BanBnXkFtZTgwMzQ1MjM1MjI@._V1_Ratio0.7727_AL_.jpg",
            "name": "David McCallum",
            "asCharacter": "Donald Mallard / ... 411 episodes, 2003-2021"
        },
        {
            "id": "nm0615266",
            "image": "https://imdb-api.com/images/original/MV5BNjMyNTU3ZWItNDlmZS00ZGQ0LWExNGItYjA0OGQyZDQ2OTQ0XkEyXkFqcGdeQXVyODIwODIzNTY@._V1_Ratio0.7727_AL_.jpg",
            "name": "Sean Murray",
            "asCharacter": "Timothy McGee / ... 397 episodes, 2003-2021"
        },
        {
            "id": "nm0005306",
            "image": "https://imdb-api.com/images/original/MV5BMTcxNzA5MDk5OV5BMl5BanBnXkFtZTcwODI1OTkyMQ@@._V1_Ratio1.2273_AL_.jpg",
            "name": "Pauley Perrette",
            "asCharacter": "Abby Sciuto 354 episodes, 2003-2018"
        },
        {
            "id": "nm1145177",
            "image": "https://imdb-api.com/images/original/MV5BMTY5MTc1NTI3OV5BMl5BanBnXkFtZTcwMDMzMzkzMQ@@._V1_Ratio0.7273_AL_.jpg",
            "name": "Brian Dietzen",
            "asCharacter": "Jimmy Palmer / ... 313 episodes, 2004-2021"
        },
        {
            "id": "nm0915762",
            "image": "https://imdb-api.com/images/original/MV5BMjEzMzExMDE3MV5BMl5BanBnXkFtZTcwMjM0NDY1OQ@@._V1_Ratio0.7273_AL_.jpg",
            "name": "Michael Weatherly",
            "asCharacter": "Anthony DiNozzo 306 episodes, 2003-2019"
        },
        {
            "id": "nm0140969",
            "image": "https://imdb-api.com/images/original/MV5BMjMwODg0OTA1MF5BMl5BanBnXkFtZTcwNTIwNjk1Nw@@._V1_Ratio0.7273_AL_.jpg",
            "name": "Rocky Carroll",
            "asCharacter": "Leon Vance / ... 304 episodes, 2008-2021"
        },
        {
            "id": "nm1580243",
            "image": "https://imdb-api.com/images/original/MV5BMTYwMDEyNTcxMV5BMl5BanBnXkFtZTcwNjM5ODQ2Ng@@._V1_Ratio0.7273_AL_.jpg",
            "name": "Cote de Pablo",
            "asCharacter": "Ziva David 195 episodes, 2005-2020"
        },
        {
            "id": "nm2278978",
            "image": "https://imdb-api.com/images/original/MV5BNmQ0ZTQxYzktMjMyYS00NjUwLTkwZDctOTBjZmM5MzJhZGNhXkEyXkFqcGdeQXVyMjQwMDg0Ng@@._V1_Ratio0.8636_AL_.jpg",
            "name": "Emily Wickersham",
            "asCharacter": "Ellie Bishop / ... 170 episodes, 2013-2021"
        }
    ],
    "fullCast": null,
    "genres": "Action, Crime, Drama, Mystery, Thriller",
    "genreList": [
        { "key": "Action", "value": "Action" },
        { "key": "Crime", "value": "Crime" },
        { "key": "Drama", "value": "Drama" },
        { "key": "Mystery", "value": "Mystery" },
        { "key": "Thriller", "value": "Thriller" }
    ],
    "companies": "Belisarius Productions, Paramount Network Television, CBS Paramount Network Television",
    "companyList": [
        { "id": "co0114905", "name": "Belisarius Productions" },
        { "id": "co0066107", "name": "Paramount Network Television" },
        { "id": "co0183875", "name": "CBS Paramount Network Television" }
    ],
    "countries": "USA",
    "countryList": [{ "key": "USA", "value": "USA" }],
    "languages": "English",
    "languageList": [{ "key": "English", "value": "English" }],
    "contentRating": "TV-14",
    "imDbRating": "7.7",
    "imDbRatingVotes": "121639",
    "metacriticRating": "51",
    "ratings": null,
    "wikipedia": null,
    "posters": {
        "imDbId": "tt0364845",
        "title": "NCIS",
        "fullTitle": "NCIS (2003– )",
        "type": "TVSeries",
        "year": "2003",
        "posters": [
            {
                "id": "lSTchtc26YNdOjdKvZtLs22SokL.jpg",
                "link": "https://imdb-api.com/posters/original/lSTchtc26YNdOjdKvZtLs22SokL.jpg",
                "aspectRatio": 0.6666666666666666,
                "language": "en",
                "width": 2000,
                "height": 3000
            },
            {
                "id": "q9TVqJSHfJPsEJGHtxHuBvOdKu9.jpg",
                "link": "https://imdb-api.com/posters/original/q9TVqJSHfJPsEJGHtxHuBvOdKu9.jpg",
                "aspectRatio": 0.6666666666666666,
                "language": "en",
                "width": 1500,
                "height": 2250
            },
            {
                "id": "fi8EvaWtL5CvoielOjjVvTr7ux3.jpg",
                "link": "https://imdb-api.com/posters/original/fi8EvaWtL5CvoielOjjVvTr7ux3.jpg",
                "aspectRatio": 0.6666666666666666,
                "language": "en",
                "width": 1400,
                "height": 2100
            },
            {
                "id": "eoj15m14Zpf2bUWXqNIs7itZK9w.jpg",
                "link": "https://imdb-api.com/posters/original/eoj15m14Zpf2bUWXqNIs7itZK9w.jpg",
                "aspectRatio": 0.6666666666666666,
                "language": "en",
                "width": 1400,
                "height": 2100
            },
            {
                "id": "wjqzKd664dRoOSZUFn12wzUuVNO.jpg",
                "link": "https://imdb-api.com/posters/original/wjqzKd664dRoOSZUFn12wzUuVNO.jpg",
                "aspectRatio": 0.6666666666666666,
                "language": "en",
                "width": 1400,
                "height": 2100
            },
            {
                "id": "ge8JYwRQj3LmnkHlP3BWHZrTUUs.jpg",
                "link": "https://imdb-api.com/posters/original/ge8JYwRQj3LmnkHlP3BWHZrTUUs.jpg",
                "aspectRatio": 0.6668900804289544,
                "language": "en",
                "width": 1990,
                "height": 2984
            },
            {
                "id": "po4ZIt6XI9kyKMLtEipZxjbeYGu.jpg",
                "link": "https://imdb-api.com/posters/original/po4ZIt6XI9kyKMLtEipZxjbeYGu.jpg",
                "aspectRatio": 0.6666666666666666,
                "language": "en",
                "width": 2000,
                "height": 3000
            },
            {
                "id": "7j7bYIfUsfwGJv3ZyitmbSRbTua.jpg",
                "link": "https://imdb-api.com/posters/original/7j7bYIfUsfwGJv3ZyitmbSRbTua.jpg",
                "aspectRatio": 0.6666666666666666,
                "language": "en",
                "width": 2000,
                "height": 3000
            },
            {
                "id": "6I9sV5MYI9O3jrJDU7zAsvPJ7Ve.jpg",
                "link": "https://imdb-api.com/posters/original/6I9sV5MYI9O3jrJDU7zAsvPJ7Ve.jpg",
                "aspectRatio": 0.6666666666666666,
                "language": "en",
                "width": 1160,
                "height": 1740
            },
            {
                "id": "uqO7fvzTzFKbWMZWmT98TfSqWg7.jpg",
                "link": "https://imdb-api.com/posters/original/uqO7fvzTzFKbWMZWmT98TfSqWg7.jpg",
                "aspectRatio": 0.68,
                "language": "en",
                "width": 680,
                "height": 1000
            },
            {
                "id": "A5hTIFhU4VeTACmfmpfqkJI4Xcf.jpg",
                "link": "https://imdb-api.com/posters/original/A5hTIFhU4VeTACmfmpfqkJI4Xcf.jpg",
                "aspectRatio": 0.68,
                "language": "en",
                "width": 680,
                "height": 1000
            },
            {
                "id": "aQZNM2uCcfcJ4MlMLGWiqfFRhEC.jpg",
                "link": "https://imdb-api.com/posters/original/aQZNM2uCcfcJ4MlMLGWiqfFRhEC.jpg",
                "aspectRatio": 0.6666666666666666,
                "language": "en",
                "width": 1000,
                "height": 1500
            },
            {
                "id": "69qAiuc6AddM0fyV5xR3w03xxP9.jpg",
                "link": "https://imdb-api.com/posters/original/69qAiuc6AddM0fyV5xR3w03xxP9.jpg",
                "aspectRatio": 0.6666666666666666,
                "language": "en",
                "width": 1000,
                "height": 1500
            },
            {
                "id": "wlCDJOev76m3R8z6zYK4hRGzPVV.jpg",
                "link": "https://imdb-api.com/posters/original/wlCDJOev76m3R8z6zYK4hRGzPVV.jpg",
                "aspectRatio": 0.68,
                "language": "en",
                "width": 680,
                "height": 1000
            },
            {
                "id": "an61rOKh5Udo6Gj7wyJ5zIokVuU.jpg",
                "link": "https://imdb-api.com/posters/original/an61rOKh5Udo6Gj7wyJ5zIokVuU.jpg",
                "aspectRatio": 0.68,
                "language": "en",
                "width": 680,
                "height": 1000
            },
            {
                "id": "9naPmi8qNCWEWpEsloiung42Hwu.jpg",
                "link": "https://imdb-api.com/posters/original/9naPmi8qNCWEWpEsloiung42Hwu.jpg",
                "aspectRatio": 0.68,
                "language": "en",
                "width": 680,
                "height": 1000
            },
            {
                "id": "qg7riUVREGz2J7050epWwZFNFFm.jpg",
                "link": "https://imdb-api.com/posters/original/qg7riUVREGz2J7050epWwZFNFFm.jpg",
                "aspectRatio": 0.6666666666666666,
                "language": "en",
                "width": 1500,
                "height": 2250
            },
            {
                "id": "23ri7fNgny0U862aZavtxzDMdpT.jpg",
                "link": "https://imdb-api.com/posters/original/23ri7fNgny0U862aZavtxzDMdpT.jpg",
                "aspectRatio": 0.6666666666666666,
                "language": "en",
                "width": 1500,
                "height": 2250
            },
            {
                "id": "hv3gRTZWgsrJIasIt6Gz6GjczfF.jpg",
                "link": "https://imdb-api.com/posters/original/hv3gRTZWgsrJIasIt6Gz6GjczfF.jpg",
                "aspectRatio": 0.6666666666666666,
                "language": "en",
                "width": 2000,
                "height": 3000
            },
            {
                "id": "4TlhNaRkwLAQxBkgYERQNulanZq.jpg",
                "link": "https://imdb-api.com/posters/original/4TlhNaRkwLAQxBkgYERQNulanZq.jpg",
                "aspectRatio": 0.6666666666666666,
                "language": "en",
                "width": 1500,
                "height": 2250
            },
            {
                "id": "un9ZQUwuQGJxKu0V035nulEqadP.jpg",
                "link": "https://imdb-api.com/posters/original/un9ZQUwuQGJxKu0V035nulEqadP.jpg",
                "aspectRatio": 0.6666666666666666,
                "language": "en",
                "width": 1400,
                "height": 2100
            },
            {
                "id": "32YEHCCaizow02AzY6VnHwqvB32.jpg",
                "link": "https://imdb-api.com/posters/original/32YEHCCaizow02AzY6VnHwqvB32.jpg",
                "aspectRatio": 0.6666666666666666,
                "language": "en",
                "width": 2000,
                "height": 3000
            }
        ],
        "backdrops": [
            {
                "id": "tMNvDXbv0YeioKlM955M9adH3ul.jpg",
                "link": "https://imdb-api.com/posters/original/tMNvDXbv0YeioKlM955M9adH3ul.jpg",
                "aspectRatio": 1.7777777777777777,
                "language": "en",
                "width": 1280,
                "height": 720
            },
            {
                "id": "949JxBlacQOYqgCK38RaXIe5uvq.jpg",
                "link": "https://imdb-api.com/posters/original/949JxBlacQOYqgCK38RaXIe5uvq.jpg",
                "aspectRatio": 1.7777777777777777,
                "language": "en",
                "width": 1280,
                "height": 720
            },
            {
                "id": "tU385Qu6yMGptCWGkkDvRT976H4.jpg",
                "link": "https://imdb-api.com/posters/original/tU385Qu6yMGptCWGkkDvRT976H4.jpg",
                "aspectRatio": 1.7777777777777777,
                "language": "en",
                "width": 1920,
                "height": 1080
            },
            {
                "id": "bE9yoQKtvvvLIi6EnmY1qcbmYzO.jpg",
                "link": "https://imdb-api.com/posters/original/bE9yoQKtvvvLIi6EnmY1qcbmYzO.jpg",
                "aspectRatio": 1.7777777777777777,
                "language": "en",
                "width": 1920,
                "height": 1080
            },
            {
                "id": "tETyYM6ZtvPBc8VHKyHlty7LZ8S.jpg",
                "link": "https://imdb-api.com/posters/original/tETyYM6ZtvPBc8VHKyHlty7LZ8S.jpg",
                "aspectRatio": 1.7777777777777777,
                "language": "en",
                "width": 1920,
                "height": 1080
            },
            {
                "id": "xlBGwQ48WupnEfaXQ1aSVaTX1FT.jpg",
                "link": "https://imdb-api.com/posters/original/xlBGwQ48WupnEfaXQ1aSVaTX1FT.jpg",
                "aspectRatio": 1.7777777777777777,
                "language": "en",
                "width": 1920,
                "height": 1080
            },
            {
                "id": "dw7cgoB1intvT7J3Ft0HMG4OeJt.jpg",
                "link": "https://imdb-api.com/posters/original/dw7cgoB1intvT7J3Ft0HMG4OeJt.jpg",
                "aspectRatio": 1.7777777777777777,
                "language": "en",
                "width": 1920,
                "height": 1080
            },
            {
                "id": "ligtQorIbGwJdPw8I4wYUGqe4dQ.jpg",
                "link": "https://imdb-api.com/posters/original/ligtQorIbGwJdPw8I4wYUGqe4dQ.jpg",
                "aspectRatio": 1.7777777777777777,
                "language": "en",
                "width": 1920,
                "height": 1080
            },
            {
                "id": "6fqaFmi1ruY4B3MQNB68DeJbom1.jpg",
                "link": "https://imdb-api.com/posters/original/6fqaFmi1ruY4B3MQNB68DeJbom1.jpg",
                "aspectRatio": 1.7777777777777777,
                "language": "en",
                "width": 1920,
                "height": 1080
            },
            {
                "id": "iL8fUdkxoptoA6cjGGTGck8xHEy.jpg",
                "link": "https://imdb-api.com/posters/original/iL8fUdkxoptoA6cjGGTGck8xHEy.jpg",
                "aspectRatio": 1.7777777777777777,
                "language": "en",
                "width": 1920,
                "height": 1080
            },
            {
                "id": "ftltZTp03sG9ajqz8VTrt4vGVKT.jpg",
                "link": "https://imdb-api.com/posters/original/ftltZTp03sG9ajqz8VTrt4vGVKT.jpg",
                "aspectRatio": 1.7777777777777777,
                "language": "en",
                "width": 1920,
                "height": 1080
            },
            {
                "id": "n4LjDhNFMHtCQ2Prjh0ZA1ioL6W.jpg",
                "link": "https://imdb-api.com/posters/original/n4LjDhNFMHtCQ2Prjh0ZA1ioL6W.jpg",
                "aspectRatio": 1.7777777777777777,
                "language": "en",
                "width": 1920,
                "height": 1080
            },
            {
                "id": "jG5tS9nqHEyMweVL9xfVhpRfujn.jpg",
                "link": "https://imdb-api.com/posters/original/jG5tS9nqHEyMweVL9xfVhpRfujn.jpg",
                "aspectRatio": 1.7777777777777777,
                "language": "en",
                "width": 1920,
                "height": 1080
            },
            {
                "id": "qmcoEOrTm6BcgR4iO7KBQKE9AKT.jpg",
                "link": "https://imdb-api.com/posters/original/qmcoEOrTm6BcgR4iO7KBQKE9AKT.jpg",
                "aspectRatio": 1.7777777777777777,
                "language": "en",
                "width": 3840,
                "height": 2160
            },
            {
                "id": "ms8XxpJwTPYaUcbwhO2kJS6SGVM.jpg",
                "link": "https://imdb-api.com/posters/original/ms8XxpJwTPYaUcbwhO2kJS6SGVM.jpg",
                "aspectRatio": 1.7777777777777777,
                "language": "en",
                "width": 1920,
                "height": 1080
            },
            {
                "id": "4VuCtYBvZGq6Rk3gloigwlsTefE.jpg",
                "link": "https://imdb-api.com/posters/original/4VuCtYBvZGq6Rk3gloigwlsTefE.jpg",
                "aspectRatio": 1.7777777777777777,
                "language": "en",
                "width": 3840,
                "height": 2160
            },
            {
                "id": "yD1R7QCNqrcaf15AxkLbgRLI9Dz.jpg",
                "link": "https://imdb-api.com/posters/original/yD1R7QCNqrcaf15AxkLbgRLI9Dz.jpg",
                "aspectRatio": 1.7777777777777777,
                "language": "en",
                "width": 1920,
                "height": 1080
            },
            {
                "id": "aNBABKjPSzJY2NlSUOyJD6CDKTR.jpg",
                "link": "https://imdb-api.com/posters/original/aNBABKjPSzJY2NlSUOyJD6CDKTR.jpg",
                "aspectRatio": 1.7777777777777777,
                "language": "en",
                "width": 3840,
                "height": 2160
            },
            {
                "id": "2ey9kXymyGInFEOQ6hgMHwD70i4.jpg",
                "link": "https://imdb-api.com/posters/original/2ey9kXymyGInFEOQ6hgMHwD70i4.jpg",
                "aspectRatio": 1.7777777777777777,
                "language": "en",
                "width": 1920,
                "height": 1080
            },
            {
                "id": "lM8rTWLQbNr2sCRsD2mUan82kcv.jpg",
                "link": "https://imdb-api.com/posters/original/lM8rTWLQbNr2sCRsD2mUan82kcv.jpg",
                "aspectRatio": 1.7777777777777777,
                "language": "en",
                "width": 1280,
                "height": 720
            },
            {
                "id": "cCjwGsBwbFmlM3eir7EV8inKZXg.jpg",
                "link": "https://imdb-api.com/posters/original/cCjwGsBwbFmlM3eir7EV8inKZXg.jpg",
                "aspectRatio": 1.7777777777777777,
                "language": "en",
                "width": 2880,
                "height": 1620
            },
            {
                "id": "siSk7Wr8zMHyRJIMpHqmHhMKKX1.jpg",
                "link": "https://imdb-api.com/posters/original/siSk7Wr8zMHyRJIMpHqmHhMKKX1.jpg",
                "aspectRatio": 1.7777777777777777,
                "language": "en",
                "width": 1280,
                "height": 720
            },
            {
                "id": "uwB6YRhNcjq7JwXHqtcqWtmnA3E.jpg",
                "link": "https://imdb-api.com/posters/original/uwB6YRhNcjq7JwXHqtcqWtmnA3E.jpg",
                "aspectRatio": 1.7777777777777777,
                "language": "en",
                "width": 1280,
                "height": 720
            },
            {
                "id": "iyWRXAywVJk6JtEMVS98nySynfm.jpg",
                "link": "https://imdb-api.com/posters/original/iyWRXAywVJk6JtEMVS98nySynfm.jpg",
                "aspectRatio": 1.7777777777777777,
                "language": "en",
                "width": 1280,
                "height": 720
            },
            {
                "id": "eEx0r54UPod07R6M3aDat799iwy.jpg",
                "link": "https://imdb-api.com/posters/original/eEx0r54UPod07R6M3aDat799iwy.jpg",
                "aspectRatio": 1.7777777777777777,
                "language": "en",
                "width": 1280,
                "height": 720
            },
            {
                "id": "kVYqvyqTh2Sk3THyX9NiNegkbq4.jpg",
                "link": "https://imdb-api.com/posters/original/kVYqvyqTh2Sk3THyX9NiNegkbq4.jpg",
                "aspectRatio": 1.7777777777777777,
                "language": "en",
                "width": 3840,
                "height": 2160
            },
            {
                "id": "bzLWRkpQcobvZSx5j4XqFr5Sj52.jpg",
                "link": "https://imdb-api.com/posters/original/bzLWRkpQcobvZSx5j4XqFr5Sj52.jpg",
                "aspectRatio": 1.7777777777777777,
                "language": "en",
                "width": 1280,
                "height": 720
            },
            {
                "id": "plpXmBlNzeSiINQNrpNuKYGgd7k.jpg",
                "link": "https://imdb-api.com/posters/original/plpXmBlNzeSiINQNrpNuKYGgd7k.jpg",
                "aspectRatio": 1.7777777777777777,
                "language": "en",
                "width": 1920,
                "height": 1080
            },
            {
                "id": "cMgTFiR5CMzXszLaQQcBvwvbDKA.jpg",
                "link": "https://imdb-api.com/posters/original/cMgTFiR5CMzXszLaQQcBvwvbDKA.jpg",
                "aspectRatio": 1.7777777777777777,
                "language": "en",
                "width": 1920,
                "height": 1080
            },
            {
                "id": "uNt1oIeD1yue3zVWKQSHAH3V7Dd.jpg",
                "link": "https://imdb-api.com/posters/original/uNt1oIeD1yue3zVWKQSHAH3V7Dd.jpg",
                "aspectRatio": 1.7777777777777777,
                "language": "en",
                "width": 2880,
                "height": 1620
            }
        ],
        "errorMessage": ""
    },
    "images": {
        "imDbId": "tt0364845",
        "title": "NCIS",
        "fullTitle": "NCIS (2003– )",
        "type": "TVSeries",
        "year": "2003",
        "items": [
            {
                "title": "Wilmer Valderrama and Sean Murray in NCIS (2003)",
                "image": "https://imdb-api.com/images/original/MV5BNWRmNDQ5MTgtNjgzMy00OWYwLWE4NWUtYzk2ZWZjNzAyYzI2XkEyXkFqcGdeQXVyNTM3MDMyMDQ@._V1_Ratio1.3200_AL_.jpg"
            },
            {
                "title": "Mark Harmon and Emily Wickersham in NCIS (2003)",
                "image": "https://imdb-api.com/images/original/MV5BNjE1Y2RlZjEtMjNhMy00MGNmLWFkMjgtODNmMmYyMGI0OGFjXkEyXkFqcGdeQXVyNTM3MDMyMDQ@._V1_Ratio1.3200_AL_.jpg"
            },
            {
                "title": "Mark Harmon, Nike Doukas, and Diona Reasonover in NCIS (2003)",
                "image": "https://imdb-api.com/images/original/MV5BOGEzM2U0NmUtODk1Mi00MWE1LWJmNTItYzliNzJlNTVkMzE0XkEyXkFqcGdeQXVyNTM3MDMyMDQ@._V1_Ratio1.3200_AL_.jpg"
            },
            {
                "title": "Wilmer Valderrama in NCIS (2003)",
                "image": "https://imdb-api.com/images/original/MV5BMWFlMzhkMTktNDI5MC00MWIwLWFhOTMtMjIwODk2OTQ0ODg4XkEyXkFqcGdeQXVyNTM3MDMyMDQ@._V1_Ratio1.3200_AL_.jpg"
            },
            {
                "title": "Mark Harmon and Emily Wickersham in NCIS (2003)",
                "image": "https://imdb-api.com/images/original/MV5BYWJkZjQxZGEtMjNhOS00ZThkLTliMzQtZjQ5ZjBjMjNkNWQ2XkEyXkFqcGdeQXVyNTM3MDMyMDQ@._V1_Ratio1.3200_AL_.jpg"
            },
            {
                "title": "Wilmer Valderrama and Sean Murray in NCIS (2003)",
                "image": "https://imdb-api.com/images/original/MV5BNTBlNGQxYTQtMWQ4Zi00NmE1LWJiNTktODJiMzE2NWRiMGEzXkEyXkFqcGdeQXVyNTM3MDMyMDQ@._V1_Ratio1.3200_AL_.jpg"
            },
            {
                "title": "Mark Harmon and Emily Wickersham in NCIS (2003)",
                "image": "https://imdb-api.com/images/original/MV5BMzg2Yjg1ODQtZmZiYS00ZmUzLWI1MzktMmU1YzY2OTcxMTEzXkEyXkFqcGdeQXVyNTM3MDMyMDQ@._V1_Ratio1.3200_AL_.jpg"
            },
            {
                "title": "Mark Harmon and Cote de Pablo in NCIS (2003)",
                "image": "https://imdb-api.com/images/original/MV5BMmI5MmEwOGEtY2FiMC00OTMzLTliNGEtN2M2MzZkN2Y2ZmJmXkEyXkFqcGdeQXVyNTM3MDMyMDQ@._V1_Ratio1.3200_AL_.jpg"
            },
            {
                "title": "Mark Harmon, Wilmer Valderrama, Sean Murray, and Emily Wickersham in NCIS (2003)",
                "image": "https://imdb-api.com/images/original/MV5BMTY3ZGFhMTEtODgzMi00ODcwLWE5NzItNjIyNmY1ODc1NDUwXkEyXkFqcGdeQXVyNTM3MDMyMDQ@._V1_Ratio1.3200_AL_.jpg"
            },
            {
                "title": "Mark Harmon in NCIS (2003)",
                "image": "https://imdb-api.com/images/original/MV5BZWNjMmJkZDQtZmMyMS00ZThhLTkzY2MtOTgxOGMxN2IwNDBjXkEyXkFqcGdeQXVyNTM3MDMyMDQ@._V1_Ratio1.3200_AL_.jpg"
            },
            {
                "title": "Mark Harmon and Diona Reasonover in NCIS (2003)",
                "image": "https://imdb-api.com/images/original/MV5BYzZkNWQzNmQtMGE4OC00YmY4LTg1ZGEtNjE0ZDc4YjNiZWU3XkEyXkFqcGdeQXVyNTM3MDMyMDQ@._V1_Ratio1.3200_AL_.jpg"
            },
            {
                "title": "Wilmer Valderrama, Sean Murray, and Emily Wickersham in NCIS (2003)",
                "image": "https://imdb-api.com/images/original/MV5BODNjZDBmNTktMjZmYi00ZTA5LWJjMjEtOTdjOWI1ZGYzNDlmXkEyXkFqcGdeQXVyNTM3MDMyMDQ@._V1_Ratio1.3200_AL_.jpg"
            },
            {
                "title": "Wilmer Valderrama in NCIS (2003)",
                "image": "https://imdb-api.com/images/original/MV5BZDhlMzBjMjgtNjhlMS00ZGYzLThjYmYtNGY2ZjhlMDE1YTQ4XkEyXkFqcGdeQXVyNTM3MDMyMDQ@._V1_Ratio1.3200_AL_.jpg"
            },
            {
                "title": "Emily Wickersham in NCIS (2003)",
                "image": "https://imdb-api.com/images/original/MV5BMTc0MjBkOTAtM2UwZi00OGQyLTk0NzEtMmU3ODk2ZWExZGY1XkEyXkFqcGdeQXVyNTM3MDMyMDQ@._V1_Ratio1.3200_AL_.jpg"
            },
            {
                "title": "Mark Harmon, Wilmer Valderrama, and Emily Wickersham in NCIS (2003)",
                "image": "https://imdb-api.com/images/original/MV5BNGIzNGZlNjEtMTNmOS00OTFiLTkyYTUtZWNhYTM3NDBlOTJlXkEyXkFqcGdeQXVyNTM3MDMyMDQ@._V1_Ratio1.3200_AL_.jpg"
            },
            {
                "title": "Mark Harmon and Maria Bello in NCIS (2003)",
                "image": "https://imdb-api.com/images/original/MV5BY2IzMzNmNGEtODY1Ny00OGExLTk0NGQtMTUyZGZmZDVjNGY4XkEyXkFqcGdeQXVyNTM3MDMyMDQ@._V1_Ratio1.3200_AL_.jpg"
            },
            {
                "title": "Mark Harmon, Wilmer Valderrama, Sean Murray, and Emily Wickersham in NCIS (2003)",
                "image": "https://imdb-api.com/images/original/MV5BMThhNGU2NWMtOTdlZS00NTE1LWExYmItOTI5MTIwYTc0OGUxXkEyXkFqcGdeQXVyNjg3MDMxNzU@._V1_Ratio1.5000_AL_.jpg"
            },
            {
                "title": "Wilmer Valderrama in NCIS (2003)",
                "image": "https://imdb-api.com/images/original/MV5BZmNkNTZiMDAtNTUzZC00YjI5LTgzMzEtMjk5MDY2NjZlNjUyXkEyXkFqcGdeQXVyNTM3MDMyMDQ@._V1_Ratio1.3200_AL_.jpg"
            },
            {
                "title": "Wilmer Valderrama in NCIS (2003)",
                "image": "https://imdb-api.com/images/original/MV5BNjEzMzY4Y2UtMTYwYy00NWRiLTlmZWYtZmE0NWQ4NGQ2NmQ5XkEyXkFqcGdeQXVyNTM3MDMyMDQ@._V1_Ratio1.3200_AL_.jpg"
            },
            {
                "title": "Mark Harmon and Sean Murray in NCIS (2003)",
                "image": "https://imdb-api.com/images/original/MV5BYTg2ZGU5ZTMtODU0Ny00ZmE1LWIwZTEtMjMxN2Y2ZTIyMzU3XkEyXkFqcGdeQXVyNDg4NjY5OTQ@._V1_Ratio1.5000_AL_.jpg"
            },
            {
                "title": "Emily Wickersham in NCIS (2003)",
                "image": "https://imdb-api.com/images/original/MV5BZGZiZTYzNTEtMTM4YS00NzA4LWJiMGItYmI1OTVlNzQ4YzNmXkEyXkFqcGdeQXVyNDg4NjY5OTQ@._V1_Ratio1.5000_AL_.jpg"
            },
            {
                "title": "Dabney Coleman and Mark Harmon in NCIS (2003)",
                "image": "https://imdb-api.com/images/original/MV5BZWVhNDBiZDYtY2U3NC00MTIyLTg0YmQtYzA3MGIyZDJjOWRlXkEyXkFqcGdeQXVyNTM3MDMyMDQ@._V1_Ratio1.3200_AL_.jpg"
            },
            {
                "title": "Sean Murray in NCIS (2003)",
                "image": "https://imdb-api.com/images/original/MV5BMDI3ZWZjNTMtMmIyZS00ZThmLWI5NmEtNmJkYmZiMWYzMmUyXkEyXkFqcGdeQXVyNjc5Mjg0NjU@._V1_Ratio1.0000_AL_.jpg"
            },
            {
                "title": "Sean Murray in NCIS (2003)",
                "image": "https://imdb-api.com/images/original/MV5BOGMyM2MwZGYtNDRiOC00MmViLTk3ODctYmYyNjdlZDlhMDk1XkEyXkFqcGdeQXVyNjc5Mjg0NjU@._V1_Ratio1.5000_AL_.jpg"
            },
            {
                "title": "Emily Wickersham in NCIS (2003)",
                "image": "https://imdb-api.com/images/original/MV5BYTQxMjY5MmMtZmMyMy00MzFlLTkyNmEtMTcyYzY4NjFjOThhXkEyXkFqcGdeQXVyNjc5Mjg0NjU@._V1_Ratio1.5000_AL_.jpg"
            },
            {
                "title": "Brian Dietzen in NCIS (2003)",
                "image": "https://imdb-api.com/images/original/MV5BOGNjNzkzY2QtODBhYi00OGIyLWIwZTctZTdjZDQ5MjZkN2JlXkEyXkFqcGdeQXVyNTM3MDMyMDQ@._V1_Ratio1.3200_AL_.jpg"
            },
            {
                "title": "Mark Harmon, Rocky Carroll, and Chris Nelson Norris in NCIS (2003)",
                "image": "https://imdb-api.com/images/original/MV5BNGUxZTU0NzQtYjBmNS00OWI1LWJmYWItMzQ4MmU4MWNjOGQ3XkEyXkFqcGdeQXVyNTM3MDMyMDQ@._V1_Ratio1.3200_AL_.jpg"
            },
            {
                "title": "NCIS (2003)",
                "image": "https://imdb-api.com/images/original/MV5BYTA3YTY4ZWMtZjFhMi00YTZjLWJkYWUtNjk3NTJlZDljNzIzXkEyXkFqcGdeQXVyNTM3MDMyMDQ@._V1_Ratio1.3200_AL_.jpg"
            },
            {
                "title": "Pauley Perrette, Brian Dietzen, and Emily Wickersham in NCIS (2003)",
                "image": "https://imdb-api.com/images/original/MV5BNTBkMTc4ZDQtODQ5ZC00OGU0LTgwY2QtZTAyZGRhY2NiOTUwXkEyXkFqcGdeQXVyNTM3MDMyMDQ@._V1_Ratio1.3200_AL_.jpg"
            },
            {
                "title": "Mark Harmon, Wilmer Valderrama, Sean Murray, and Emily Wickersham in NCIS (2003)",
                "image": "https://imdb-api.com/images/original/MV5BYTI0NDE3NzQtNjM4Zi00OTJlLWEwZWEtZTcyMTc3MmQ2MmI2XkEyXkFqcGdeQXVyNTM3MDMyMDQ@._V1_Ratio1.3200_AL_.jpg"
            },
            {
                "title": "Mark Harmon in NCIS (2003)",
                "image": "https://imdb-api.com/images/original/MV5BNWIwNTU5ZWUtODBlMC00MjY3LTg3OTktMzc5MDEzNGYzMGIwXkEyXkFqcGdeQXVyNTM3MDMyMDQ@._V1_Ratio1.3200_AL_.jpg"
            },
            {
                "title": "Mark Harmon in NCIS (2003)",
                "image": "https://imdb-api.com/images/original/MV5BNDQ5NGNiMmEtY2VmMC00NjBmLWE5MzYtYjFiNDI4NzM3MTdiXkEyXkFqcGdeQXVyNTM3MDMyMDQ@._V1_Ratio1.3200_AL_.jpg"
            },
            {
                "title": "Mark Harmon, Rocky Carroll, and Joe Spano in NCIS (2003)",
                "image": "https://imdb-api.com/images/original/MV5BMzA4MjNjMmQtZTFiNC00YTJkLTliOGYtOWEzMWQzYTlhMThjXkEyXkFqcGdeQXVyNTM3MDMyMDQ@._V1_Ratio1.3200_AL_.jpg"
            },
            {
                "title": "Michael Weatherly and Cote de Pablo in NCIS (2003)",
                "image": "https://imdb-api.com/images/original/MV5BOTIzZGI0MjEtNDBhYi00OGU0LTgwNzMtMDZiODUxMzZmZGQ5XkEyXkFqcGdeQXVyNTM3MDMyMDQ@._V1_Ratio1.3200_AL_.jpg"
            },
            {
                "title": "Pauley Perrette, Sean Murray, and Duane Henry in NCIS (2003)",
                "image": "https://imdb-api.com/images/original/MV5BMWNlMzI3ODItMmFlZS00Yzk3LThhNDctMzVkN2ZlODMxNjk2XkEyXkFqcGdeQXVyNTM3MDMyMDQ@._V1_Ratio1.3200_AL_.jpg"
            },
            {
                "title": "Sean Murray in NCIS (2003)",
                "image": "https://imdb-api.com/images/original/MV5BNmVmNjJiOGYtYTc1Yy00ZmEyLWIyMDgtNDhkOWIwNDJkZWZmXkEyXkFqcGdeQXVyNTM3MDMyMDQ@._V1_Ratio1.3200_AL_.jpg"
            },
            {
                "title": "Mark Harmon and Patrick Labyorteaux in NCIS (2003)",
                "image": "https://imdb-api.com/images/original/MV5BZWRkMjY0MmEtMmMzNS00ODdlLWFiNmYtMDQ5MzFmN2Y1ZTBkXkEyXkFqcGdeQXVyNTM3MDMyMDQ@._V1_Ratio1.3200_AL_.jpg"
            },
            {
                "title": "Mark Harmon and Emily Wickersham in NCIS (2003)",
                "image": "https://imdb-api.com/images/original/MV5BZGFmMmY3MmQtNzZhOS00YjhiLTgzN2YtODA0NDE5MDllM2NlXkEyXkFqcGdeQXVyNTM3MDMyMDQ@._V1_Ratio1.3200_AL_.jpg"
            },
            {
                "title": "Maria Bello in NCIS (2003)",
                "image": "https://imdb-api.com/images/original/MV5BNzE5MDdkYTgtNWU3My00NjFmLWI5NzktMWE0MDc5NDc0NTAwXkEyXkFqcGdeQXVyNTM3MDMyMDQ@._V1_Ratio1.3200_AL_.jpg"
            },
            {
                "title": "Mark Harmon in NCIS (2003)",
                "image": "https://imdb-api.com/images/original/MV5BMDI0Y2MwMjYtNjZlNC00MjM3LTlkZTktYjkzMTc5YjhmN2ViXkEyXkFqcGdeQXVyNTM3MDMyMDQ@._V1_Ratio1.3200_AL_.jpg"
            },
            {
                "title": "Pauley Perrette in NCIS (2003)",
                "image": "https://imdb-api.com/images/original/MV5BNWYzMDhjMzgtMzU2YS00ZGMyLWI1MjYtZWM1YjNmNzkyNzY0XkEyXkFqcGdeQXVyNTM3MDMyMDQ@._V1_Ratio1.3200_AL_.jpg"
            },
            {
                "title": "Mark Harmon, Rocky Carroll, and David McCallum in NCIS (2003)",
                "image": "https://imdb-api.com/images/original/MV5BYjVlNDM3MjktNThhYS00ZGM4LTkyOWMtYWVmZGE2MzQ2ODRkXkEyXkFqcGdeQXVyNTM3MDMyMDQ@._V1_Ratio1.3200_AL_.jpg"
            },
            {
                "title": "Pauley Perrette, Wilmer Valderrama, Sean Murray, and Emily Wickersham in NCIS (2003)",
                "image": "https://imdb-api.com/images/original/MV5BODJhYTI0NWYtNjVkNi00YzgwLWIzNWQtOTJiYmY2YjgxZDMxXkEyXkFqcGdeQXVyNTM3MDMyMDQ@._V1_Ratio1.3200_AL_.jpg"
            },
            {
                "title": "Maria Bello and Pauley Perrette in NCIS (2003)",
                "image": "https://imdb-api.com/images/original/MV5BNWYzOWEzOTUtZTY3MC00NWM1LTljZTAtODcyZjhlNzlmNzA4XkEyXkFqcGdeQXVyNTM3MDMyMDQ@._V1_Ratio1.3200_AL_.jpg"
            },
            {
                "title": "Duane Henry and Emily Wickersham in NCIS (2003)",
                "image": "https://imdb-api.com/images/original/MV5BNDdkNDU1Y2MtNjEzYS00ZjM5LTgyOGEtZTRkNzM1NDcyMzRhXkEyXkFqcGdeQXVyNTM3MDMyMDQ@._V1_Ratio1.3200_AL_.jpg"
            },
            {
                "title": "Mark Harmon, Maria Bello, and Brian Dietzen in NCIS (2003)",
                "image": "https://imdb-api.com/images/original/MV5BNDJkNTEyODItNjY2Ni00ZDdhLTgyMTYtN2QyYzEwMTc4ODc2XkEyXkFqcGdeQXVyNTM3MDMyMDQ@._V1_Ratio1.3200_AL_.jpg"
            },
            {
                "title": "Emily Wickersham in NCIS (2003)",
                "image": "https://imdb-api.com/images/original/MV5BNmMzNDEwYzMtZTM1OS00ZjEzLWI3ZDQtNjU5OTBhODFiZjFkXkEyXkFqcGdeQXVyNjc5Mjg0NjU@._V1_Ratio1.0000_AL_.jpg"
            },
            {
                "title": "Mark Harmon, Wilmer Valderrama, Sean Murray, and Emily Wickersham in NCIS (2003)",
                "image": "https://imdb-api.com/images/original/MV5BMjZhNjA4ODItYzVmNC00YWZjLWJjOWQtNzliZDRhMDllZTE0XkEyXkFqcGdeQXVyNjc5Mjg0NjU@._V1_Ratio1.5000_AL_.jpg"
            }
        ],
        "errorMessage": ""
    },
    "trailer": {
        "imDbId": "tt0364845",
        "title": "NCIS",
        "fullTitle": "NCIS (TV Series 2003– )",
        "type": "TVSeries",
        "year": "2003",
        "videoId": "vi291414809",
        "videoTitle": "NCIS: The Eigth Season",
        "videoDescription": "Trailer for NCIS: The Eighth Season",
        "thumbnailUrl": "https://m.media-amazon.com/images/M/MV5BZDJiZmZiNGUtNWFhMi00MzM0LWEzMjAtMTM2NzMyYzQzMjg5XkEyXkFqcGdeQXVyNzU1NzE3NTg@._V1_.jpg",
        "uploadDate": "05/02/2012 03:22:41",
        "link": "https://www.imdb.com/video/vi291414809",
        "linkEmbed": "https://www.imdb.com/video/imdb/vi291414809/imdb/embed",
        "errorMessage": ""
    },
    "boxOffice": {
        "budget": "",
        "openingWeekendUSA": "",
        "grossUSA": "",
        "cumulativeWorldwideGross": ""
    },
    "tagline": "",
    "keywords": "goth girl,babe scientist,special agent,naval criminal investigative service,police procedural",
    "keywordList": [
        "goth girl",
        "babe scientist",
        "special agent",
        "naval criminal investigative service",
        "police procedural"
    ],
    "similars": [
        {
            "id": "tt0452046",
            "title": "Criminal Minds",
            "fullTitle": "Criminal Minds (2005–2020)",
            "year": "2005–2020",
            "image": "https://imdb-api.com/images/original/MV5BNGE2ZmFkZTYtNjRiOS00ZjE3LThjOWMtZTViZjRmNDFjNTQwXkEyXkFqcGdeQXVyNjg4NzAyOTA@._V1_Ratio0.6737_AL_.jpg",
            "plot": "The cases of the F.B.I. Behavioral Analysis Unit (B.A.U.), an elite group of profilers who analyze the nation's most dangerous serial killers and individual heinous crimes in an effort to anticipate their next moves before they strike again.",
            "directors": "",
            "stars": "Matthew Gray Gubler, Kirsten Vangsness, A.J. Cook",
            "genres": "Crime, Drama, Mystery",
            "imDbRating": "8.1"
        },
        {
            "id": "tt1378167",
            "title": "NCIS: Los Angeles",
            "fullTitle": "NCIS: Los Angeles (TV Series 2009)",
            "year": "TV Series 2009",
            "image": "https://imdb-api.com/images/original/MV5BMGQzNGIzNmEtNWE3ZS00OTUyLTg3YTEtMDY3NDViZWE0YWY1XkEyXkFqcGdeQXVyNjg4NzAyOTA@._V1_Ratio0.6737_AL_.jpg",
            "plot": "The Naval Criminal Investigation Service's Office of Special Projects takes on the undercover work and the hard to crack cases in LA. Key agents are G. Callen and Sam Hanna, streets kids risen through the ranks.",
            "directors": "",
            "stars": "Chris O'Donnell, Daniela Ruah, Barrett Foa",
            "genres": "Action, Crime, Drama",
            "imDbRating": "6.7"
        },
        {
            "id": "tt0203259",
            "title": "Law &amp; Order: Special Victims Unit",
            "fullTitle": "Law &amp; Order: Special Victims Unit (TV Series 1999)",
            "year": "TV Series 1999",
            "image": "https://imdb-api.com/images/original/MV5BNWNlNjcwNGItOWRkNi00MzI0LTg3OGMtYzdjZDA4YmU4M2U1XkEyXkFqcGdeQXVyODUxOTU0OTg@._V1_Ratio0.6737_AL_.jpg",
            "plot": "This series follows the Special Victims Unit, a specially trained squad of detectives in the N.Y.P.D., who investigate sexually related crimes.",
            "directors": "",
            "stars": "Mariska Hargitay, Christopher Meloni, Ice-T",
            "genres": "Crime, Drama, Mystery",
            "imDbRating": "8"
        },
        {
            "id": "tt3560084",
            "title": "NCIS: New Orleans",
            "fullTitle": "NCIS: New Orleans (2014–2021)",
            "year": "2014–2021",
            "image": "https://imdb-api.com/images/original/MV5BMjM3OTk1NTQyNF5BMl5BanBnXkFtZTgwMjU4NDQwMDI@._V1_Ratio0.6737_AL_.jpg",
            "plot": "A spin-off of NCIS (2003) about the local field office of NCIS that investigates criminal cases involving military personnel in The Big Easy, a city known for its music, entertainment and decadence. This colorful city that harbors a dark side is a magnet for service personnel on leave, and when overindulgence is followed by trouble, Special Agent Dwayne Pride's team is at its best.",
            "directors": "",
            "stars": "Scott Bakula, Rob Kerkovich, CCH Pounder",
            "genres": "Crime, Drama, Mystery",
            "imDbRating": "6.8"
        },
        {
            "id": "tt2741602",
            "title": "The Blacklist",
            "fullTitle": "The Blacklist (TV Series 2013)",
            "year": "TV Series 2013",
            "image": "https://imdb-api.com/images/original/MV5BZDA1MzE3M2EtNTE4Ni00OGE4LWE1NjctYzFhMzA2NDgxMDIxXkEyXkFqcGdeQXVyODUxOTU0OTg@._V1_Ratio0.6737_AL_.jpg",
            "plot": "A new FBI profiler, Elizabeth Keen, has her entire life uprooted when a mysterious criminal, Raymond Reddington, who has eluded capture for decades, turns himself in and insists on speaking only to her.",
            "directors": "",
            "stars": "James Spader, Megan Boone, Diego Klattenhoff",
            "genres": "Crime, Drama, Mystery",
            "imDbRating": "8"
        },
        {
            "id": "tt0460627",
            "title": "Bones",
            "fullTitle": "Bones (2005–2017)",
            "year": "2005–2017",
            "image": "https://imdb-api.com/images/original/MV5BMjA3ODMxMzM5NF5BMl5BanBnXkFtZTgwMDM1NjU0OTE@._V1_Ratio0.6737_AL_.jpg",
            "plot": "Forensic anthropologist Dr. Temperance \"Bones\" Brennan and cocky F.B.I. Special Agent Seeley Booth build a team to investigate murders. Quite often, there isn't more to examine than rotten flesh or mere bones.",
            "directors": "",
            "stars": "Emily Deschanel, David Boreanaz, Michaela Conlin",
            "genres": "Comedy, Crime, Drama",
            "imDbRating": "7.8"
        },
        {
            "id": "tt0413573",
            "title": "Grey's Anatomy",
            "fullTitle": "Grey's Anatomy (TV Series 2005)",
            "year": "TV Series 2005",
            "image": "https://imdb-api.com/images/original/MV5BMjgwNGNkZGYtMWQyYS00YjEzLWFmZTctODUzYWMxOWJkNTAzXkEyXkFqcGdeQXVyMTkxNjUyNQ@@._V1_Ratio0.6737_AL_.jpg",
            "plot": "A drama centered on the personal and professional lives of five surgical interns and their supervisors.",
            "directors": "",
            "stars": "Ellen Pompeo, Chandra Wilson, James Pickens Jr.",
            "genres": "Drama, Romance",
            "imDbRating": "7.6"
        },
        {
            "id": "tt0460681",
            "title": "Supernatural",
            "fullTitle": "Supernatural (2005–2020)",
            "year": "2005–2020",
            "image": "https://imdb-api.com/images/original/MV5BNzRmZWJhNjUtY2ZkYy00N2MyLWJmNTktOTAwY2VkODVmOGY3XkEyXkFqcGdeQXVyMTkxNjUyNQ@@._V1_Ratio0.6737_AL_.jpg",
            "plot": "Two brothers follow their father's footsteps as hunters, fighting evil supernatural beings of many kinds, including monsters, demons and gods that roam the earth.",
            "directors": "",
            "stars": "Jared Padalecki, Jensen Ackles, Jim Beaver",
            "genres": "Drama, Fantasy, Horror",
            "imDbRating": "8.4"
        },
        {
            "id": "tt3107288",
            "title": "The Flash",
            "fullTitle": "The Flash (TV Series 2014)",
            "year": "TV Series 2014",
            "image": "https://imdb-api.com/images/original/MV5BMDIzNzYwNTctZWY4Mi00YjQ2LWI5YWYtMzdmNDgwMGI4Yzk1XkEyXkFqcGdeQXVyMTkxNjUyNQ@@._V1_Ratio0.8000_AL_.jpg",
            "plot": "After being struck by lightning, Barry Allen wakes up from his coma to discover he's been given the power of super speed, becoming the next Flash, fighting crime in Central City.",
            "directors": "",
            "stars": "Grant Gustin, Candice Patton, Danielle Panabaker",
            "genres": "Action, Adventure, Drama",
            "imDbRating": "7.7"
        },
        {
            "id": "tt1442437",
            "title": "Modern Family",
            "fullTitle": "Modern Family (2009–2020)",
            "year": "2009–2020",
            "image": "https://imdb-api.com/images/original/MV5BNzRhNWIxYTEtYjc2NS00YWFlLWFhOGEtMDZiMWM1M2RkNDkyXkEyXkFqcGdeQXVyNjc0MjkzNjc@._V1_Ratio0.6737_AL_.jpg",
            "plot": "Three different but related families face trials and tribulations in their own uniquely comedic ways.",
            "directors": "",
            "stars": "Ed O'Neill, Sofía Vergara, Julie Bowen",
            "genres": "Comedy, Drama, Romance",
            "imDbRating": "8.4"
        },
        {
            "id": "tt1219024",
            "title": "Castle",
            "fullTitle": "Castle (2009–2016)",
            "year": "2009–2016",
            "image": "https://imdb-api.com/images/original/MV5BMjM2NjU0ODU0NF5BMl5BanBnXkFtZTgwMDAwMzg5NjE@._V1_Ratio0.6737_AL_.jpg",
            "plot": "After a serial killer imitates the plots of his novels, successful mystery novelist Richard \"Rick\" Castle receives permission from the Mayor of New York City to tag along with an NYPD homicide investigation team for research purposes.",
            "directors": "",
            "stars": "Nathan Fillion, Stana Katic, Susan Sullivan",
            "genres": "Comedy, Crime, Drama",
            "imDbRating": "8.1"
        },
        {
            "id": "tt0108778",
            "title": "Friends",
            "fullTitle": "Friends (1994–2004)",
            "year": "1994–2004",
            "image": "https://imdb-api.com/images/original/MV5BNDVkYjU0MzctMWRmZi00NTkxLTgwZWEtOWVhYjZlYjllYmU4XkEyXkFqcGdeQXVyNTA4NzY1MzY@._V1_Ratio0.6737_AL_.jpg",
            "plot": "Follows the personal and professional lives of six twenty to thirty-something-year-old friends living in Manhattan.",
            "directors": "",
            "stars": "Jennifer Aniston, Courteney Cox, Lisa Kudrow",
            "genres": "Comedy, Romance",
            "imDbRating": "8.9"
        }
    ],
    "tvSeriesInfo": {
        "yearEnd": "",
        "creators": "Donald P. Bellisario, Don McGill",
        "creatorList": [
            { "id": "nm0069074", "name": "Donald P. Bellisario" },
            { "id": "nm1453745", "name": "Don McGill" }
        ],
        "seasons": [
            "1",
            "2",
            "3",
            "4",
            "5",
            "6",
            "7",
            "8",
            "9",
            "10",
            "11",
            "12",
            "13",
            "14",
            "15",
            "16",
            "17",
            "18"
        ]
    },
    "tvEpisodeInfo": null,
    "errorMessage": ""
}
