{
    "id": "tt2442560",
    "title": "Peaky Blinders",
    "originalTitle": "",
    "fullTitle": "Peaky Blinders (2013– )",
    "type": "TVSeries",
    "year": "2013",
    "image": "https://imdb-api.com/images/original/MV5BMTkzNjEzMDEzMF5BMl5BanBnXkFtZTgwMDI0MjE4MjE@._V1_Ratio0.6762_AL_.jpg",
    "releaseDate": "2014-09-29",
    "runtimeMins": "",
    "runtimeStr": "",
    "plot": "Thomas Shelby and his brothers return to Birmingham after serving in the British Army during WWI. Shelby and the Peaky Blinders, the gang he is leader of, control the city of Birmingham But as Shelby's ambitions extend beyond Birmingham, he plans to build on the business empire he's created, and stop anyone who gets in his way.",
    "plotLocal": "",
    "plotLocalIsRtl": false,
    "awards": "Top rated TV #69 | Awards22 wins & 47 nominations total",
    "directors": "",
    "directorList": [],
    "writers": "",
    "writerList": [],
    "stars": "Cillian Murphy, Paul Anderson, Helen McCrory",
    "starList": [
        { "id": "nm0614165", "name": "Cillian Murphy" },
        { "id": "nm2167957", "name": "Paul Anderson" },
        { "id": "nm0567031", "name": "Helen McCrory" }
    ],
    "actorList": [
        {
            "id": "nm0614165",
            "image": "https://imdb-api.com/images/original/MV5BMTUzMjg1NzIyOV5BMl5BanBnXkFtZTYwMzg2Mjgy._V1_Ratio1.0000_AL_.jpg",
            "name": "Cillian Murphy",
            "asCharacter": "Thomas Shelbyas Thomas Shelby"
        },
        {
            "id": "nm2167957",
            "image": "https://imdb-api.com/images/original/MV5BNzQ5ZTk5MGUtYjRmYi00NTIzLWFlYjMtZjk5MGFlNTg5ODViXkEyXkFqcGdeQXVyMzIzNjk4NzM@._V1_Ratio1.0000_AL_.jpg",
            "name": "Paul Anderson",
            "asCharacter": "Arthur Shelbyas Arthur Shelby"
        },
        {
            "id": "nm0567031",
            "image": "https://imdb-api.com/images/original/MV5BMTQ2MDM2OTU0MV5BMl5BanBnXkFtZTgwMDk2MTIzNTE@._V1_Ratio1.5000_AL_.jpg",
            "name": "Helen McCrory",
            "asCharacter": "Aunt Pollyas Aunt Polly…"
        },
        {
            "id": "nm2570706",
            "image": "https://imdb-api.com/images/original/MV5BMzIwODI2NzY2OV5BMl5BanBnXkFtZTgwNDk5Mjc0ODE@._V1_Ratio1.0000_AL_.jpg",
            "name": "Sophie Rundle",
            "asCharacter": "Ada Shelbyas Ada Shelby"
        },
        {
            "id": "nm0219329",
            "image": "https://imdb-api.com/images/original/MV5BYzYyNjY3MTUtZWQ4MC00MjQ4LTliNTItMDMwNDczYjQyZDIzXkEyXkFqcGdeQXVyMjQwMDg0Ng@@._V1_Ratio1.0000_AL_.jpg",
            "name": "Ned Dennehy",
            "asCharacter": "Charlie Strongas Charlie Strong"
        },
        {
            "id": "nm6806440",
            "image": "https://imdb-api.com/images/original/MV5BMTEwMzQzODYwNzVeQTJeQWpwZ15BbWU4MDEyODU2NTMx._V1_Ratio1.3571_AL_.jpg",
            "name": "Finn Cole",
            "asCharacter": "Michael Grayas Michael Gray"
        },
        {
            "id": "nm0669667",
            "image": "https://imdb-api.com/images/original/MV5BZWUzZThhZjktMDU3OC00ZmYxLWIxYjgtYWVhNWZmYmMyZDE4XkEyXkFqcGdeQXVyNzE4NjI2NzI@._V1_Ratio1.0000_AL_.jpg",
            "name": "Ian Peck",
            "asCharacter": "Curlyas Curly"
        },
        {
            "id": "nm6804376",
            "image": "https://imdb-api.com/images/original/MV5BNzQzNzE1NDg2NV5BMl5BanBnXkFtZTgwOTIwOTgzNDM@._V1_Ratio1.0000_AL_.jpg",
            "name": "Harry Kirton",
            "asCharacter": "Finn Shelbyas Finn Shelby"
        },
        {
            "id": "nm3771184",
            "image": "https://imdb-api.com/images/original/MV5BOGJkZWZmZmYtOTZlMC00ZjBjLTg3Y2EtOTJiZTVmMTg5NGE0XkEyXkFqcGdeQXVyMjY2NzQyNTg@._V1_Ratio1.0000_AL_.jpg",
            "name": "Joe Cole",
            "asCharacter": "John Shelbyas John Shelby"
        },
        {
            "id": "nm3761798",
            "image": "https://imdb-api.com/images/original/MV5BZmRmYjQ1MTEtYjZkOC00YjUyLTllODgtYzdiOTg3Y2UyM2NmXkEyXkFqcGdeQXVyMjI3NzYyOTA@._V1_Ratio1.0000_AL_.jpg",
            "name": "Natasha O'Keeffe",
            "asCharacter": "Lizzie Starkas Lizzie Stark"
        },
        {
            "id": "nm0497970",
            "image": "https://imdb-api.com/images/original/MV5BMWE1YWI3YzUtZmY4ZC00YjRjLThiN2QtMjczMGUyMzY5NzBkXkEyXkFqcGdeQXVyMjY5OTcxMDg@._V1_Ratio1.0000_AL_.jpg",
            "name": "Packy Lee",
            "asCharacter": "Johnny Dogsas Johnny Dogs"
        },
        {
            "id": "nm1834115",
            "image": "https://imdb-api.com/images/original/MV5BMTc2NjM5MTUzNl5BMl5BanBnXkFtZTcwNzQyOTM2Nw@@._V1_Ratio1.0000_AL_.jpg",
            "name": "Annabelle Wallis",
            "asCharacter": "Grace Burgessas Grace Burgess…"
        },
        {
            "id": "nm7056012",
            "image": "https://imdb-api.com/images/original/MV5BMDRjYWU4YTktNzNjNy00MzIzLWI4YzctNmQwMjk1MmIzZjM5XkEyXkFqcGdeQXVyMjQwMDg0Ng@@._V1_Ratio1.0000_AL_.jpg",
            "name": "Kate Phillips",
            "asCharacter": "Linda Shelbyas Linda Shelby"
        },
        {
            "id": "nm0686029",
            "image": "https://imdb-api.com/images/original/MV5BMTk1NzI5NjM2N15BMl5BanBnXkFtZTgwNTA0NDEzMDI@._V1_Ratio1.3429_AL_.jpg",
            "name": "Tony Pitts",
            "asCharacter": "Sergeant Mossas Sergeant Moss…"
        },
        {
            "id": "nm2929682",
            "image": "https://imdb-api.com/images/original/MV5BMjI3NzgwOTExNF5BMl5BanBnXkFtZTgwNTc5NTAxODE@._V1_Ratio1.5143_AL_.jpg",
            "name": "Aimee-Ffion Edwards",
            "asCharacter": "Esme Shelbyas Esme Shelby"
        },
        {
            "id": "nm6304865",
            "image": "https://imdb-api.com/images/original/MV5BYjE2NzJlZjQtMWUzNy00ZDNjLWIyODAtOWRkOWQ4MThlNGY1XkEyXkFqcGdeQXVyMTUxNzU2OQ@@._V1_Ratio1.0000_AL_.jpg",
            "name": "Jordan Bolger",
            "asCharacter": "Isiahas Isiah…"
        },
        {
            "id": "nm0000554",
            "image": "https://imdb-api.com/images/original/MV5BMjUyMTU0MzA0MF5BMl5BanBnXkFtZTgwNTA4MTQ4NjM@._V1_Ratio1.0000_AL_.jpg",
            "name": "Sam Neill",
            "asCharacter": "Inspector Chester Campbellas Inspector Chester Campbell…"
        },
        {
            "id": "nm0362766",
            "image": "https://imdb-api.com/images/original/MV5BMTQ3ODEyNjA4Nl5BMl5BanBnXkFtZTgwMTE4ODMyMjE@._V1_Ratio1.0000_AL_.jpg",
            "name": "Tom Hardy",
            "asCharacter": "Alfie Solomonsas Alfie Solomons"
        }
    ],
    "fullCast": null,
    "genres": "Crime, Drama",
    "genreList": [
        { "key": "Crime", "value": "Crime" },
        { "key": "Drama", "value": "Drama" }
    ],
    "companies": "Caryn Mandabach Productions, Tiger Aspect Productions, British Broadcasting Corporation (BBC)",
    "companyList": [
        { "id": "co0275656", "name": "Caryn Mandabach Productions" },
        { "id": "co0103644", "name": "Tiger Aspect Productions" },
        { "id": "co0043107", "name": "British Broadcasting Corporation (BBC)" }
    ],
    "countries": "UK",
    "countryList": [{ "key": "UK", "value": "UK" }],
    "languages": "Italian, Yiddish, English, Romanian, Irish Gaelic",
    "languageList": [
        { "key": "Italian", "value": "Italian" },
        { "key": "Yiddish", "value": "Yiddish" },
        { "key": "English", "value": "English" },
        { "key": "Romanian", "value": "Romanian" },
        { "key": "Irish Gaelic", "value": "Irish Gaelic" }
    ],
    "contentRating": "TV-MA",
    "imDbRating": "8.8",
    "imDbRatingVotes": "384504",
    "metacriticRating": "",
    "ratings": null,
    "wikipedia": null,
    "posters": {
        "imDbId": "tt2442560",
        "title": "Peaky Blinders",
        "fullTitle": "Peaky Blinders (2013– )",
        "type": "TVSeries",
        "year": "2013",
        "posters": [
            {
                "id": "bGZn5RVzMMXju4ev7xbl1aLdXqq.jpg",
                "link": "https://imdb-api.com/posters/original/bGZn5RVzMMXju4ev7xbl1aLdXqq.jpg",
                "aspectRatio": 0.6666666666666666,
                "language": "en",
                "width": 2000,
                "height": 3000
            },
            {
                "id": "pE8CScObQURsFZ723PSW1K9EGYp.jpg",
                "link": "https://imdb-api.com/posters/original/pE8CScObQURsFZ723PSW1K9EGYp.jpg",
                "aspectRatio": 0.6666666666666666,
                "language": "en",
                "width": 1000,
                "height": 1500
            },
            {
                "id": "6PX0r5TRRU5y0jZ70y1OtbLYmoD.jpg",
                "link": "https://imdb-api.com/posters/original/6PX0r5TRRU5y0jZ70y1OtbLYmoD.jpg",
                "aspectRatio": 0.6666666666666666,
                "language": "en",
                "width": 1200,
                "height": 1800
            },
            {
                "id": "se86cWSwdSftjJH8OStW7Yu3ZPC.jpg",
                "link": "https://imdb-api.com/posters/original/se86cWSwdSftjJH8OStW7Yu3ZPC.jpg",
                "aspectRatio": 0.7501442585112522,
                "language": "en",
                "width": 1300,
                "height": 1733
            },
            {
                "id": "oqRZFXubClzWvxufuijg5Ls2mNW.jpg",
                "link": "https://imdb-api.com/posters/original/oqRZFXubClzWvxufuijg5Ls2mNW.jpg",
                "aspectRatio": 0.674,
                "language": "en",
                "width": 674,
                "height": 1000
            },
            {
                "id": "9yebAvhk6phqPHp7I7Z4ToVKKBZ.jpg",
                "link": "https://imdb-api.com/posters/original/9yebAvhk6phqPHp7I7Z4ToVKKBZ.jpg",
                "aspectRatio": 0.6747638326585695,
                "language": "en",
                "width": 1000,
                "height": 1482
            },
            {
                "id": "cLUFl9acoYKODsvZNFG0zcWhNU7.jpg",
                "link": "https://imdb-api.com/posters/original/cLUFl9acoYKODsvZNFG0zcWhNU7.jpg",
                "aspectRatio": 0.68,
                "language": "en",
                "width": 680,
                "height": 1000
            },
            {
                "id": "RYX6zJni4vgvCtzfZKG3cXr3np.jpg",
                "link": "https://imdb-api.com/posters/original/RYX6zJni4vgvCtzfZKG3cXr3np.jpg",
                "aspectRatio": 0.68,
                "language": "en",
                "width": 680,
                "height": 1000
            },
            {
                "id": "k6q16xNtG2Hhf1m9AhnB5WnWrQa.jpg",
                "link": "https://imdb-api.com/posters/original/k6q16xNtG2Hhf1m9AhnB5WnWrQa.jpg",
                "aspectRatio": 0.68,
                "language": "en",
                "width": 680,
                "height": 1000
            },
            {
                "id": "avTW19nOr1w2ApBRVm8ECKb6tb.jpg",
                "link": "https://imdb-api.com/posters/original/avTW19nOr1w2ApBRVm8ECKb6tb.jpg",
                "aspectRatio": 0.68,
                "language": "en",
                "width": 680,
                "height": 1000
            },
            {
                "id": "fCJlgQBahlRzwsunLJV85eFILaA.jpg",
                "link": "https://imdb-api.com/posters/original/fCJlgQBahlRzwsunLJV85eFILaA.jpg",
                "aspectRatio": 0.68,
                "language": "en",
                "width": 680,
                "height": 1000
            },
            {
                "id": "i8i0jOCn0SpM6xz5gQxDQ1LABgo.jpg",
                "link": "https://imdb-api.com/posters/original/i8i0jOCn0SpM6xz5gQxDQ1LABgo.jpg",
                "aspectRatio": 0.68,
                "language": "en",
                "width": 680,
                "height": 1000
            },
            {
                "id": "bRQTLvu0EoRm946lweQKoPC6oBU.jpg",
                "link": "https://imdb-api.com/posters/original/bRQTLvu0EoRm946lweQKoPC6oBU.jpg",
                "aspectRatio": 0.68,
                "language": "en",
                "width": 680,
                "height": 1000
            },
            {
                "id": "1XTKe7tDncj4i98bFIP5AbisR58.jpg",
                "link": "https://imdb-api.com/posters/original/1XTKe7tDncj4i98bFIP5AbisR58.jpg",
                "aspectRatio": 0.68,
                "language": "en",
                "width": 680,
                "height": 1000
            },
            {
                "id": "sAchqhHmec8Z8wly82a5YGKsWQF.jpg",
                "link": "https://imdb-api.com/posters/original/sAchqhHmec8Z8wly82a5YGKsWQF.jpg",
                "aspectRatio": 0.68,
                "language": "en",
                "width": 680,
                "height": 1000
            },
            {
                "id": "sAxcavHBU8Fv6yXYEBOBmwiSDl2.jpg",
                "link": "https://imdb-api.com/posters/original/sAxcavHBU8Fv6yXYEBOBmwiSDl2.jpg",
                "aspectRatio": 0.68,
                "language": "en",
                "width": 680,
                "height": 1000
            },
            {
                "id": "q1aC54M1hQISniMrwPJvxKdiHOC.jpg",
                "link": "https://imdb-api.com/posters/original/q1aC54M1hQISniMrwPJvxKdiHOC.jpg",
                "aspectRatio": 0.68,
                "language": "en",
                "width": 680,
                "height": 1000
            },
            {
                "id": "vFwUHEgjPovlpXER2AZsMckShFh.jpg",
                "link": "https://imdb-api.com/posters/original/vFwUHEgjPovlpXER2AZsMckShFh.jpg",
                "aspectRatio": 0.68,
                "language": "en",
                "width": 680,
                "height": 1000
            },
            {
                "id": "mW7tQ1HKA9h3ZUk7ODyN1qbtSmm.jpg",
                "link": "https://imdb-api.com/posters/original/mW7tQ1HKA9h3ZUk7ODyN1qbtSmm.jpg",
                "aspectRatio": 0.68,
                "language": "en",
                "width": 680,
                "height": 1000
            },
            {
                "id": "120Z5bDwbta9j0Zumi3vlfzWJ9V.jpg",
                "link": "https://imdb-api.com/posters/original/120Z5bDwbta9j0Zumi3vlfzWJ9V.jpg",
                "aspectRatio": 0.68,
                "language": "en",
                "width": 680,
                "height": 1000
            },
            {
                "id": "npIbt7RnHXuXIAOLHwBmK1I32fC.jpg",
                "link": "https://imdb-api.com/posters/original/npIbt7RnHXuXIAOLHwBmK1I32fC.jpg",
                "aspectRatio": 0.68,
                "language": "en",
                "width": 680,
                "height": 1000
            },
            {
                "id": "ky4IIpGFT1BHID7oQdwUK0Lg0lZ.jpg",
                "link": "https://imdb-api.com/posters/original/ky4IIpGFT1BHID7oQdwUK0Lg0lZ.jpg",
                "aspectRatio": 0.68,
                "language": "en",
                "width": 680,
                "height": 1000
            },
            {
                "id": "PnmIG148mNmUPzJwGXsErRIsgq.jpg",
                "link": "https://imdb-api.com/posters/original/PnmIG148mNmUPzJwGXsErRIsgq.jpg",
                "aspectRatio": 0.68,
                "language": "en",
                "width": 680,
                "height": 1000
            },
            {
                "id": "nyA6PF0vGVdbTfjJUqsjbKHGeDq.jpg",
                "link": "https://imdb-api.com/posters/original/nyA6PF0vGVdbTfjJUqsjbKHGeDq.jpg",
                "aspectRatio": 0.667,
                "language": "en",
                "width": 1334,
                "height": 2000
            },
            {
                "id": "7llbcNpFWUnPY8IwIwy9J0F7wGI.jpg",
                "link": "https://imdb-api.com/posters/original/7llbcNpFWUnPY8IwIwy9J0F7wGI.jpg",
                "aspectRatio": 0.6666666666666666,
                "language": "en",
                "width": 2000,
                "height": 3000
            },
            {
                "id": "AtJ3p0kbD6gcCggmPdjh2ltNzQm.jpg",
                "link": "https://imdb-api.com/posters/original/AtJ3p0kbD6gcCggmPdjh2ltNzQm.jpg",
                "aspectRatio": 0.6666666666666666,
                "language": "en",
                "width": 1000,
                "height": 1500
            }
        ],
        "backdrops": [
            {
                "id": "l8v3gJDlASN0lNn51gR8zQJsu5O.jpg",
                "link": "https://imdb-api.com/posters/original/l8v3gJDlASN0lNn51gR8zQJsu5O.jpg",
                "aspectRatio": 1.7777777777777777,
                "language": "en",
                "width": 3840,
                "height": 2160
            },
            {
                "id": "wiE9doxiLwq3WCGamDIOb2PqBqc.jpg",
                "link": "https://imdb-api.com/posters/original/wiE9doxiLwq3WCGamDIOb2PqBqc.jpg",
                "aspectRatio": 1.7777777777777777,
                "language": "en",
                "width": 1920,
                "height": 1080
            },
            {
                "id": "1c5wA3y9K8WRwQRcU8oGFRNJ7Yn.jpg",
                "link": "https://imdb-api.com/posters/original/1c5wA3y9K8WRwQRcU8oGFRNJ7Yn.jpg",
                "aspectRatio": 1.7777777777777777,
                "language": "en",
                "width": 1920,
                "height": 1080
            },
            {
                "id": "oDj5dCxdsR2ZmmangqNCYS9cxBH.jpg",
                "link": "https://imdb-api.com/posters/original/oDj5dCxdsR2ZmmangqNCYS9cxBH.jpg",
                "aspectRatio": 1.7777777777777777,
                "language": "en",
                "width": 1920,
                "height": 1080
            },
            {
                "id": "1OG6OV6UWmHYyRqVBJ2iGyTtbLL.jpg",
                "link": "https://imdb-api.com/posters/original/1OG6OV6UWmHYyRqVBJ2iGyTtbLL.jpg",
                "aspectRatio": 1.7777777777777777,
                "language": "en",
                "width": 1920,
                "height": 1080
            },
            {
                "id": "6n63aBdgPH22PzNgd1kcDZlmwkM.jpg",
                "link": "https://imdb-api.com/posters/original/6n63aBdgPH22PzNgd1kcDZlmwkM.jpg",
                "aspectRatio": 1.7777777777777777,
                "language": "en",
                "width": 1920,
                "height": 1080
            },
            {
                "id": "oLVk8OFX9oDDDkd41pIQ20ND2ph.jpg",
                "link": "https://imdb-api.com/posters/original/oLVk8OFX9oDDDkd41pIQ20ND2ph.jpg",
                "aspectRatio": 1.7777777777777777,
                "language": "en",
                "width": 1920,
                "height": 1080
            },
            {
                "id": "xqwY1TqwKECESoMnSpitrNGN5OO.jpg",
                "link": "https://imdb-api.com/posters/original/xqwY1TqwKECESoMnSpitrNGN5OO.jpg",
                "aspectRatio": 1.7777777777777777,
                "language": "en",
                "width": 3840,
                "height": 2160
            },
            {
                "id": "kfUWupX3phYp7AleZA2U1dmVcjX.jpg",
                "link": "https://imdb-api.com/posters/original/kfUWupX3phYp7AleZA2U1dmVcjX.jpg",
                "aspectRatio": 1.7777777777777777,
                "language": "en",
                "width": 3840,
                "height": 2160
            },
            {
                "id": "fYQVNTzh6F6PT5Eg8rQiXH09WfB.jpg",
                "link": "https://imdb-api.com/posters/original/fYQVNTzh6F6PT5Eg8rQiXH09WfB.jpg",
                "aspectRatio": 1.7777777777777777,
                "language": "en",
                "width": 2048,
                "height": 1152
            },
            {
                "id": "p6p6YPFCw2ZuC1qDXlehrvxBIBq.jpg",
                "link": "https://imdb-api.com/posters/original/p6p6YPFCw2ZuC1qDXlehrvxBIBq.jpg",
                "aspectRatio": 1.7777777777777777,
                "language": "en",
                "width": 1280,
                "height": 720
            },
            {
                "id": "ampJLuZrf163Q3kDfuNsA36w84Q.jpg",
                "link": "https://imdb-api.com/posters/original/ampJLuZrf163Q3kDfuNsA36w84Q.jpg",
                "aspectRatio": 1.7777777777777777,
                "language": "en",
                "width": 1920,
                "height": 1080
            },
            {
                "id": "kyuCxajS8Ag0QAiB59keQH66cG0.jpg",
                "link": "https://imdb-api.com/posters/original/kyuCxajS8Ag0QAiB59keQH66cG0.jpg",
                "aspectRatio": 1.7777777777777777,
                "language": "en",
                "width": 1920,
                "height": 1080
            },
            {
                "id": "n8efGaafd9xFGuTfQfQe4QjTGEn.jpg",
                "link": "https://imdb-api.com/posters/original/n8efGaafd9xFGuTfQfQe4QjTGEn.jpg",
                "aspectRatio": 1.7777777777777777,
                "language": "en",
                "width": 1920,
                "height": 1080
            },
            {
                "id": "ze045ZGfy7qXD1aw3WdcGVEBUaC.jpg",
                "link": "https://imdb-api.com/posters/original/ze045ZGfy7qXD1aw3WdcGVEBUaC.jpg",
                "aspectRatio": 1.7777777777777777,
                "language": "en",
                "width": 1920,
                "height": 1080
            },
            {
                "id": "aZ8687CZtAQKk7irjO11sxPt92z.jpg",
                "link": "https://imdb-api.com/posters/original/aZ8687CZtAQKk7irjO11sxPt92z.jpg",
                "aspectRatio": 1.7777777777777777,
                "language": "en",
                "width": 1920,
                "height": 1080
            },
            {
                "id": "6o4VHzNqrhQbBHaoPZlgtverqwB.jpg",
                "link": "https://imdb-api.com/posters/original/6o4VHzNqrhQbBHaoPZlgtverqwB.jpg",
                "aspectRatio": 1.7777777777777777,
                "language": "en",
                "width": 1920,
                "height": 1080
            },
            {
                "id": "jqmabgC7bT6pViDNISd4qWB1kzT.jpg",
                "link": "https://imdb-api.com/posters/original/jqmabgC7bT6pViDNISd4qWB1kzT.jpg",
                "aspectRatio": 1.7777777777777777,
                "language": "en",
                "width": 1920,
                "height": 1080
            },
            {
                "id": "or7wKwv1IT6LEOktt395O5qi7e.jpg",
                "link": "https://imdb-api.com/posters/original/or7wKwv1IT6LEOktt395O5qi7e.jpg",
                "aspectRatio": 1.7783046828689981,
                "language": "en",
                "width": 3000,
                "height": 1687
            },
            {
                "id": "i2Ozw3FjaQ6ZwLkBsUit7KrcOgl.jpg",
                "link": "https://imdb-api.com/posters/original/i2Ozw3FjaQ6ZwLkBsUit7KrcOgl.jpg",
                "aspectRatio": 1.7777777777777777,
                "language": "en",
                "width": 3840,
                "height": 2160
            },
            {
                "id": "ytQrbnfvblnbNRGoHAKsSrAo3B0.jpg",
                "link": "https://imdb-api.com/posters/original/ytQrbnfvblnbNRGoHAKsSrAo3B0.jpg",
                "aspectRatio": 1.7777777777777777,
                "language": "en",
                "width": 3840,
                "height": 2160
            },
            {
                "id": "dzq83RHwQcnP6WGJ6YkenIqeaa5.jpg",
                "link": "https://imdb-api.com/posters/original/dzq83RHwQcnP6WGJ6YkenIqeaa5.jpg",
                "aspectRatio": 1.7777777777777777,
                "language": "en",
                "width": 1920,
                "height": 1080
            }
        ],
        "errorMessage": ""
    },
    "images": {
        "imDbId": "tt2442560",
        "title": "Peaky Blinders",
        "fullTitle": "Peaky Blinders (2013– )",
        "type": "TVSeries",
        "year": "2013",
        "items": [
            {
                "title": "Aidan Gillen in Peaky Blinders (2013)",
                "image": "https://imdb-api.com/images/original/MV5BNDcwOGE3OGEtM2E4Mi00YWY1LTlhODktNTE5MTA0NDJkODc1XkEyXkFqcGdeQXVyMDM2NDM2MQ@@._V1_Ratio1.5000_AL_.jpg"
            },
            {
                "title": "Natasha O'Keeffe in Peaky Blinders (2013)",
                "image": "https://imdb-api.com/images/original/MV5BMTA3NDdlNDYtYzcxMi00ZWUxLTg5OWMtNWIwNGQ2OWMxODY5XkEyXkFqcGdeQXVyMDM2NDM2MQ@@._V1_Ratio1.0000_AL_.jpg"
            },
            {
                "title": "Adrien Brody in Peaky Blinders (2013)",
                "image": "https://imdb-api.com/images/original/MV5BYThlYmM0YTAtYTAyZi00YjVmLWExNDYtNzkxZDM0NjUzNWJjXkEyXkFqcGdeQXVyMDM2NDM2MQ@@._V1_Ratio1.0000_AL_.jpg"
            },
            {
                "title": "Tom Hardy in Peaky Blinders (2013)",
                "image": "https://imdb-api.com/images/original/MV5BZTFkZDBkNjYtNzk0MS00MmQ1LWI1ZTEtYjFmYzg1OGJkZDY2XkEyXkFqcGdeQXVyMDM2NDM2MQ@@._V1_Ratio1.0000_AL_.jpg"
            },
            {
                "title": "Cillian Murphy in Peaky Blinders (2013)",
                "image": "https://imdb-api.com/images/original/MV5BYTQ2Yjk0MDgtZTQ0Mi00YTc1LWE1NTAtN2JlZmEwNTg5MzE1XkEyXkFqcGdeQXVyMDM2NDM2MQ@@._V1_Ratio1.5000_AL_.jpg"
            },
            {
                "title": "Cillian Murphy in Peaky Blinders (2013)",
                "image": "https://imdb-api.com/images/original/MV5BZjQ2NjEwYTAtNjdlZi00YTMzLTljZmYtZTA2OGM3ZGRmNWJkXkEyXkFqcGdeQXVyMDM2NDM2MQ@@._V1_Ratio1.5000_AL_.jpg"
            },
            {
                "title": "Finn Cole in Peaky Blinders (2013)",
                "image": "https://imdb-api.com/images/original/MV5BYzYyZGYyMWEtZDgxMS00OGQyLWI2YzYtZjRkNzg0Y2UxZmI5XkEyXkFqcGdeQXVyMDM2NDM2MQ@@._V1_Ratio1.5000_AL_.jpg"
            },
            {
                "title": "Cillian Murphy in Peaky Blinders (2013)",
                "image": "https://imdb-api.com/images/original/MV5BYTkzYjMwN2MtYzk4MS00YWMxLWI3NDktODQwMGVhN2JkODI0XkEyXkFqcGdeQXVyMDM2NDM2MQ@@._V1_Ratio1.5000_AL_.jpg"
            },
            {
                "title": "Cillian Murphy in Peaky Blinders (2013)",
                "image": "https://imdb-api.com/images/original/MV5BMDNmMTRmOGEtNjM3NC00MGRlLTg3ZjctODg1Yjc1ZDhmOWZlXkEyXkFqcGdeQXVyMDM2NDM2MQ@@._V1_Ratio1.4800_AL_.jpg"
            },
            {
                "title": "Natasha O'Keeffe in Peaky Blinders (2013)",
                "image": "https://imdb-api.com/images/original/MV5BYjIyOGNiMzktMmYxYS00MjE0LTljMTEtOGMxZGVhYjI0M2UwXkEyXkFqcGdeQXVyMDM2NDM2MQ@@._V1_Ratio1.5000_AL_.jpg"
            },
            {
                "title": "Paul Anderson in Peaky Blinders (2013)",
                "image": "https://imdb-api.com/images/original/MV5BMDFhMmY3OTgtZDI4Yi00ZDRkLWJkZTgtMDc2NWFjMzVmNTdiXkEyXkFqcGdeQXVyMDM2NDM2MQ@@._V1_Ratio1.5000_AL_.jpg"
            },
            {
                "title": "Cillian Murphy in Peaky Blinders (2013)",
                "image": "https://imdb-api.com/images/original/MV5BODM4NzY0ZDktM2IwZC00MDFhLTlmOGYtMjU0MjI5OTQ4NDRiXkEyXkFqcGdeQXVyMDM2NDM2MQ@@._V1_Ratio1.5000_AL_.jpg"
            },
            {
                "title": "Jack Rowan in Peaky Blinders (2013)",
                "image": "https://imdb-api.com/images/original/MV5BMzFlZWZmMDMtOWE3Ni00ZDFlLWI0ZjYtNzU0YTkwNjJiYTcxXkEyXkFqcGdeQXVyMDM2NDM2MQ@@._V1_Ratio1.5000_AL_.jpg"
            },
            {
                "title": "Harry Kirton in Peaky Blinders (2013)",
                "image": "https://imdb-api.com/images/original/MV5BNWVhNDQyMzItOTkyNi00ZGI2LTkyZjMtZDEyYTEyYTVmNDFjXkEyXkFqcGdeQXVyMDM2NDM2MQ@@._V1_Ratio1.5000_AL_.jpg"
            },
            {
                "title": "Cillian Murphy in Peaky Blinders (2013)",
                "image": "https://imdb-api.com/images/original/MV5BOGE0MDJkZDYtODQzZS00ZjAyLWFjOTAtMTgyOTFmNDlkZTU2XkEyXkFqcGdeQXVyMDM2NDM2MQ@@._V1_Ratio1.0000_AL_.jpg"
            },
            {
                "title": "Kate Phillips in Peaky Blinders (2013)",
                "image": "https://imdb-api.com/images/original/MV5BZGU0MWE4M2MtOWZhNC00NjNkLThkZTMtMmQ3MzI3YzAwNDAzXkEyXkFqcGdeQXVyMDM2NDM2MQ@@._V1_Ratio1.0000_AL_.jpg"
            },
            {
                "title": "Sophie Rundle in Peaky Blinders (2013)",
                "image": "https://imdb-api.com/images/original/MV5BNTRjZTU5ODUtNDFlYi00ZjViLWE4MzAtZDFkNWJiZjYyNjVjXkEyXkFqcGdeQXVyMDM2NDM2MQ@@._V1_Ratio1.5000_AL_.jpg"
            },
            {
                "title": "Helen McCrory in Peaky Blinders (2013)",
                "image": "https://imdb-api.com/images/original/MV5BMjlkOWNiNmItNWQxMC00NzZkLTk4MmQtNGJhOTg5NDZkNGYyXkEyXkFqcGdeQXVyMDM2NDM2MQ@@._V1_Ratio1.5000_AL_.jpg"
            },
            {
                "title": "Adrien Brody in Peaky Blinders (2013)",
                "image": "https://imdb-api.com/images/original/MV5BMTYxNjg3NzY1OF5BMl5BanBnXkFtZTgwMDM5NTczNDM@._V1_Ratio1.7800_AL_.jpg"
            },
            {
                "title": "Cillian Murphy in Peaky Blinders (2013)",
                "image": "https://imdb-api.com/images/original/MV5BMTY1MWExNjQtODdmOC00ODg3LWJhMDQtNjc5MzZjNTM5MmQ0XkEyXkFqcGdeQXVyNTM3MDMyMDQ@._V1_Ratio1.3200_AL_.jpg"
            },
            {
                "title": "Cillian Murphy in Peaky Blinders (2013)",
                "image": "https://imdb-api.com/images/original/MV5BNWEwNjZlNTMtNjc2My00NGY3LTg3NjctNGEzYzk0YjgxOTg4XkEyXkFqcGdeQXVyNTM3MDMyMDQ@._V1_Ratio1.3200_AL_.jpg"
            },
            {
                "title": "Cillian Murphy in Peaky Blinders (2013)",
                "image": "https://imdb-api.com/images/original/MV5BNTMyMGYyMTItYTU4Yi00YTIyLThmZTEtN2EzMWVjZjdlNjNkXkEyXkFqcGdeQXVyNTM3MDMyMDQ@._V1_Ratio1.3200_AL_.jpg"
            },
            {
                "title": "Paul Anderson in Peaky Blinders (2013)",
                "image": "https://imdb-api.com/images/original/MV5BN2QzNTMwYzEtNDVmYS00ODA4LTg3YTQtM2FiYjdiMDdjNjAyXkEyXkFqcGdeQXVyNTM3MDMyMDQ@._V1_Ratio1.3200_AL_.jpg"
            },
            {
                "title": "Cillian Murphy in Peaky Blinders (2013)",
                "image": "https://imdb-api.com/images/original/MV5BMTg0NzI3NDYtYTY3My00OWZlLTk2YjItMTNiN2YzYjBmODZiXkEyXkFqcGdeQXVyNTM3MDMyMDQ@._V1_Ratio1.3200_AL_.jpg"
            },
            {
                "title": "Tom Hardy in Peaky Blinders (2013)",
                "image": "https://imdb-api.com/images/original/MV5BZGMzODA5YmQtZWI5MS00M2RlLTgzMTYtZmYxNWRkODRiNDZmXkEyXkFqcGdeQXVyNTM3MDMyMDQ@._V1_Ratio1.3200_AL_.jpg"
            },
            {
                "title": "Sam Neill and Helen McCrory in Peaky Blinders (2013)",
                "image": "https://imdb-api.com/images/original/MV5BODJkZGU0YTQtODU2MC00Njg0LTkwMDgtNGVlMTJhZjRjYmQ4XkEyXkFqcGdeQXVyNTM3MDMyMDQ@._V1_Ratio1.3200_AL_.jpg"
            },
            {
                "title": "Cillian Murphy in Peaky Blinders (2013)",
                "image": "https://imdb-api.com/images/original/MV5BMWFlNTlhYmQtZTNjZC00Nzg3LWJjN2UtZDZlZWIzMjVjNmU4XkEyXkFqcGdeQXVyNTM3MDMyMDQ@._V1_Ratio1.3200_AL_.jpg"
            },
            {
                "title": "Cillian Murphy in Peaky Blinders (2013)",
                "image": "https://imdb-api.com/images/original/MV5BYjNhMGNiYTYtMTViYS00NTk0LWEwNmMtMzkyN2VmNTgwYTNiXkEyXkFqcGdeQXVyNTM3MDMyMDQ@._V1_Ratio1.3200_AL_.jpg"
            },
            {
                "title": "Cillian Murphy in Peaky Blinders (2013)",
                "image": "https://imdb-api.com/images/original/MV5BOGRjN2ZlZjgtMTBiMC00N2VhLWFiNTktZTliNGJhNTJiZDQwXkEyXkFqcGdeQXVyNTM3MDMyMDQ@._V1_Ratio1.3200_AL_.jpg"
            },
            {
                "title": "Annabelle Wallis in Peaky Blinders (2013)",
                "image": "https://imdb-api.com/images/original/MV5BMTg2OTkxMWUtYzcxYi00NDRlLWIzMGItZjk4NDNmMzFjMjgzXkEyXkFqcGdeQXVyNTM3MDMyMDQ@._V1_Ratio1.3200_AL_.jpg"
            },
            {
                "title": "Cillian Murphy and Joe Cole in Peaky Blinders (2013)",
                "image": "https://imdb-api.com/images/original/MV5BODgyMWVmNDYtZDcyOS00OWUzLWEyOTAtYTA4Nzk1NGQyMTEyXkEyXkFqcGdeQXVyNTM3MDMyMDQ@._V1_Ratio1.3200_AL_.jpg"
            },
            {
                "title": "Cillian Murphy in Peaky Blinders (2013)",
                "image": "https://imdb-api.com/images/original/MV5BNjY2MjAxMjc2Ml5BMl5BanBnXkFtZTgwMjcxNjU5ODE@._V1_Ratio1.5000_AL_.jpg"
            },
            {
                "title": "Tom Hardy in Peaky Blinders (2013)",
                "image": "https://imdb-api.com/images/original/MV5BMTU2NjY1MTE0Nl5BMl5BanBnXkFtZTgwNTMwODM4MjE@._V1_Ratio1.5000_AL_.jpg"
            },
            {
                "title": "Cillian Murphy, Paul Anderson, and Joe Cole in Peaky Blinders (2013)",
                "image": "https://imdb-api.com/images/original/MV5BMTQ0NDM3MjczMV5BMl5BanBnXkFtZTgwMTIwODM4MjE@._V1_Ratio1.5000_AL_.jpg"
            },
            {
                "title": "Cillian Murphy in Peaky Blinders (2013)",
                "image": "https://imdb-api.com/images/original/MV5BNjc4MzgyODQxNF5BMl5BanBnXkFtZTgwNDIwODM4MjE@._V1_Ratio1.5000_AL_.jpg"
            },
            {
                "title": "Tom Hardy in Peaky Blinders (2013)",
                "image": "https://imdb-api.com/images/original/MV5BMTU0NTgxMDE0MV5BMl5BanBnXkFtZTgwNjIwODM4MjE@._V1_Ratio1.0000_AL_.jpg"
            },
            {
                "title": "Noah Taylor and Sam Hazeldine in Peaky Blinders (2013)",
                "image": "https://imdb-api.com/images/original/MV5BOTQ5MzA1NjAyMV5BMl5BanBnXkFtZTgwNDMwODM4MjE@._V1_Ratio1.5000_AL_.jpg"
            },
            {
                "title": "Ned Dennehy, Cillian Murphy, and Charlotte Riley in Peaky Blinders (2013)",
                "image": "https://imdb-api.com/images/original/MV5BODM5MDI4NTE5MV5BMl5BanBnXkFtZTgwMDEwODM4MjE@._V1_Ratio1.5000_AL_.jpg"
            },
            {
                "title": "Cillian Murphy in Peaky Blinders (2013)",
                "image": "https://imdb-api.com/images/original/MV5BMTAwNTQ5MzE0OTleQTJeQWpwZ15BbWU4MDExMDgzODIx._V1_Ratio1.5000_AL_.jpg"
            },
            {
                "title": "Cillian Murphy and Benjamin Zephaniah in Peaky Blinders (2013)",
                "image": "https://imdb-api.com/images/original/MV5BMjI1OTgzMjIzM15BMl5BanBnXkFtZTgwMjEwODM4MjE@._V1_Ratio1.5000_AL_.jpg"
            },
            {
                "title": "Sophie Rundle in Peaky Blinders (2013)",
                "image": "https://imdb-api.com/images/original/MV5BMTU5ODA2NjQ5N15BMl5BanBnXkFtZTgwMzEwODM4MjE@._V1_Ratio1.5000_AL_.jpg"
            },
            {
                "title": "Paul Anderson in Peaky Blinders (2013)",
                "image": "https://imdb-api.com/images/original/MV5BMTU0ODM0NDMzNl5BMl5BanBnXkFtZTgwMDIwODM4MjE@._V1_Ratio1.5000_AL_.jpg"
            },
            {
                "title": "Cillian Murphy, Paul Anderson, and Joe Cole in Peaky Blinders (2013)",
                "image": "https://imdb-api.com/images/original/MV5BMTUxMTUwNDQ0N15BMl5BanBnXkFtZTgwMjc5NzM4MjE@._V1_Ratio1.5000_AL_.jpg"
            },
            {
                "title": "Helen McCrory and Cillian Murphy in Peaky Blinders (2013)",
                "image": "https://imdb-api.com/images/original/MV5BMzc3MTAxODI3MV5BMl5BanBnXkFtZTgwMTg5NzM4MjE@._V1_Ratio1.5000_AL_.jpg"
            },
            {
                "title": "Helen McCrory and Cillian Murphy in Peaky Blinders (2013)",
                "image": "https://imdb-api.com/images/original/MV5BNDc1OTEwMDkwN15BMl5BanBnXkFtZTgwOTg5NzM4MjE@._V1_Ratio1.5000_AL_.jpg"
            },
            {
                "title": "Helen McCrory and Adam Lawrence in Peaky Blinders (2013)",
                "image": "https://imdb-api.com/images/original/MV5BMTc3MDM4ODk1MV5BMl5BanBnXkFtZTgwMDk5NzM4MjE@._V1_Ratio1.5000_AL_.jpg"
            },
            {
                "title": "Cillian Murphy in Peaky Blinders (2013)",
                "image": "https://imdb-api.com/images/original/MV5BMTY5MTcxODI2N15BMl5BanBnXkFtZTgwODk5NzM4MjE@._V1_Ratio1.5000_AL_.jpg"
            },
            {
                "title": "Cillian Murphy and Charlotte Riley in Peaky Blinders (2013)",
                "image": "https://imdb-api.com/images/original/MV5BMTkxMjM2NjA5Ml5BMl5BanBnXkFtZTgwNTY5NzM4MjE@._V1_Ratio1.5000_AL_.jpg"
            }
        ],
        "errorMessage": ""
    },
    "trailer": {
        "imDbId": "tt2442560",
        "title": "Peaky Blinders",
        "fullTitle": "Peaky Blinders (TV Series 2013– )",
        "type": "TVSeries",
        "year": "2013",
        "videoId": "vi1301724953",
        "videoTitle": "Season 5 Trailer",
        "videoDescription": "As the Shelbys grapple with the 1929 stock market crash, Tommy confronts new threats to his power from younger family members and fascist rivals. Peaky Blinders returns, October 4th.",
        "thumbnailUrl": "https://m.media-amazon.com/images/M/MV5BMWIxMGMwMzUtN2YzNy00OTQ1LWJiZmUtMjBiMzhkNGQ0MjJjXkEyXkFqcGdeQXRyYW5zY29kZS13b3JrZmxvdw@@._V1_.jpg",
        "uploadDate": "09/19/2019 15:52:05",
        "link": "https://www.imdb.com/video/vi1301724953",
        "linkEmbed": "https://www.imdb.com/video/imdb/vi1301724953/imdb/embed",
        "errorMessage": ""
    },
    "boxOffice": {
        "budget": "",
        "openingWeekendUSA": "",
        "grossUSA": "",
        "cumulativeWorldwideGross": ""
    },
    "tagline": "The streets are theirs.",
    "keywords": "gypsy,1920s,gangster,birmingham england,race fixing",
    "keywordList": [
        "gypsy",
        "1920s",
        "gangster",
        "birmingham england",
        "race fixing"
    ],
    "similars": [
        {
            "id": "tt0903747",
            "title": "Breaking Bad",
            "fullTitle": "Breaking Bad",
            "year": "",
            "image": "https://imdb-api.com/images/original/MV5BMjhiMzgxZTctNDc1Ni00OTIxLTlhMTYtZTA3ZWFkODRkNmE2XkEyXkFqcGdeQXVyNzkwMjQ5NzM@._V1_Ratio0.7246_AL_.jpg",
            "plot": "",
            "directors": "",
            "stars": "",
            "genres": "",
            "imDbRating": "9.4"
        },
        {
            "id": "tt4574334",
            "title": "Stranger Things",
            "fullTitle": "Stranger Things",
            "year": "",
            "image": "https://imdb-api.com/images/original/MV5BN2ZmYjg1YmItNWQ4OC00YWM0LWE0ZDktYThjOTZiZjhhN2Q2XkEyXkFqcGdeQXVyNjgxNTQ3Mjk@._V1_Ratio0.6763_AL_.jpg",
            "plot": "",
            "directors": "",
            "stars": "",
            "genres": "",
            "imDbRating": "8.7"
        },
        {
            "id": "tt0944947",
            "title": "Game of Thrones",
            "fullTitle": "Game of Thrones",
            "year": "",
            "image": "https://imdb-api.com/images/original/MV5BYTRiNDQwYzAtMzVlZS00NTI5LWJjYjUtMzkwNTUzMWMxZTllXkEyXkFqcGdeQXVyNDIzMzcwNjc@._V1_Ratio0.7343_AL_.jpg",
            "plot": "",
            "directors": "",
            "stars": "",
            "genres": "",
            "imDbRating": "9.3"
        },
        {
            "id": "tt6468322",
            "title": "Money Heist",
            "fullTitle": "Money Heist",
            "year": "",
            "image": "https://imdb-api.com/images/original/MV5BZDcxOGI0MDYtNTc5NS00NDUzLWFkOTItNDIxZjI0OTllNTljXkEyXkFqcGdeQXVyMTMxODk2OTU@._V1_Ratio0.6763_AL_.jpg",
            "plot": "",
            "directors": "",
            "stars": "",
            "genres": "",
            "imDbRating": "8.3"
        },
        {
            "id": "tt2306299",
            "title": "Vikings",
            "fullTitle": "Vikings",
            "year": "",
            "image": "https://imdb-api.com/images/original/MV5BODk4ZjU0NDUtYjdlOS00OTljLTgwZTUtYjkyZjk1NzExZGIzXkEyXkFqcGdeQXVyMDM2NDM2MQ@@._V1_Ratio0.6763_AL_.jpg",
            "plot": "",
            "directors": "",
            "stars": "",
            "genres": "",
            "imDbRating": "8.5"
        },
        {
            "id": "tt1475582",
            "title": "Sherlock",
            "fullTitle": "Sherlock",
            "year": "",
            "image": "https://imdb-api.com/images/original/MV5BMWY3NTljMjEtYzRiMi00NWM2LTkzNjItZTVmZjE0MTdjMjJhL2ltYWdlL2ltYWdlXkEyXkFqcGdeQXVyNTQ4NTc5OTU@._V1_Ratio0.6763_AL_.jpg",
            "plot": "",
            "directors": "",
            "stars": "",
            "genres": "",
            "imDbRating": "9.1"
        },
        {
            "id": "tt2707408",
            "title": "Narcos",
            "fullTitle": "Narcos",
            "year": "",
            "image": "https://imdb-api.com/images/original/MV5BNmFjODU3YzgtMGUwNC00ZGI3LWFkZjQtMjkxZDc3NmQ1MzcyXkEyXkFqcGdeQXVyNjUwNzk3NDc@._V1_Ratio0.6763_AL_.jpg",
            "plot": "",
            "directors": "",
            "stars": "",
            "genres": "",
            "imDbRating": "8.8"
        },
        {
            "id": "tt7366338",
            "title": "Chernobyl",
            "fullTitle": "Chernobyl",
            "year": "",
            "image": "https://imdb-api.com/images/original/MV5BZGQ2YmMxZmEtYjI5OS00NzlkLTlkNTEtYWMyMzkyMzc2MDU5XkEyXkFqcGdeQXVyMzQ2MDI5NjU@._V1_Ratio0.6763_AL_.jpg",
            "plot": "",
            "directors": "",
            "stars": "",
            "genres": "",
            "imDbRating": "9.4"
        },
        {
            "id": "tt5753856",
            "title": "Dark",
            "fullTitle": "Dark",
            "year": "",
            "image": "https://imdb-api.com/images/original/MV5BOTk2NzUyOTctZDdlMS00MDJlLTgzNTEtNzQzYjFhNjA0YjBjXkEyXkFqcGdeQXVyMjg1NDcxNDE@._V1_Ratio0.6763_AL_.jpg",
            "plot": "",
            "directors": "",
            "stars": "",
            "genres": "",
            "imDbRating": "8.8"
        },
        {
            "id": "tt10048342",
            "title": "The Queen's Gambit",
            "fullTitle": "The Queen's Gambit",
            "year": "",
            "image": "https://imdb-api.com/images/original/MV5BM2EwMmRhMmUtMzBmMS00ZDQ3LTg4OGEtNjlkODk3ZTMxMmJlXkEyXkFqcGdeQXVyMjM5ODk1NDU@._V1_Ratio0.6763_AL_.jpg",
            "plot": "",
            "directors": "",
            "stars": "",
            "genres": "",
            "imDbRating": "8.6"
        },
        {
            "id": "tt1190634",
            "title": "The Boys",
            "fullTitle": "The Boys",
            "year": "",
            "image": "https://imdb-api.com/images/original/MV5BNGEyOGJiNWEtMTgwMi00ODU4LTlkMjItZWI4NjFmMzgxZGY2XkEyXkFqcGdeQXVyNjcyNjcyMzQ@._V1_Ratio0.6763_AL_.jpg",
            "plot": "",
            "directors": "",
            "stars": "",
            "genres": "",
            "imDbRating": "8.7"
        },
        {
            "id": "tt5180504",
            "title": "The Witcher",
            "fullTitle": "The Witcher",
            "year": "",
            "image": "https://imdb-api.com/images/original/MV5BOGE4MmVjMDgtMzIzYy00NjEwLWJlODMtMDI1MGY2ZDlhMzE2XkEyXkFqcGdeQXVyMzY0MTE3NzU@._V1_Ratio0.6763_AL_.jpg",
            "plot": "",
            "directors": "",
            "stars": "",
            "genres": "",
            "imDbRating": "8.2"
        }
    ],
    "tvSeriesInfo": {
        "yearEnd": "",
        "creators": "Steven Knight",
        "creatorList": [{ "id": "nm1140275", "name": "Steven Knight" }],
        "seasons": ["1", "2", "3", "4", "5"]
    },
    "tvEpisodeInfo": null,
    "errorMessage": ""
}
